[{"Type":"FSD","Name":"Faster FSD Boot Sequence","Engineers":["Felicity Farseer","Elvira Martuuk","Professor Palin","Bris Dekker"],"Ingredients":[{"Name":"Grid Resistors","Size":1,"Kind":0}],"Favorite":false,"Ignored":false,"Grade":1},{"Type":"FSD","Name":"Faster FSD Boot Sequence","Engineers":["Felicity Farseer","Elvira Martuuk","Professor Palin","Bris Dekker"],"Ingredients":[{"Name":"Chromium","Size":1,"Kind":0},{"Name":"Grid Resistors","Size":1,"Kind":0},{"Name":"Micro Controllers","Size":1,"Kind":2}],"Favorite":false,"Ignored":false,"Grade":2},{"Type":"FSD","Name":"Faster FSD Boot Sequence","Engineers":["Felicity Farseer","Elvira Martuuk","Professor Palin","Bris Dekker"],"Ingredients":[{"Name":"Grid Resistors","Size":1,"Kind":0},{"Name":"Heat Dispersion Plate","Size":1,"Kind":0},{"Name":"Selenium","Size":1,"Kind":0},{"Name":"Hardware Diagnostic Sensor","Size":1,"Kind":2}],"Favorite":false,"Ignored":false,"Grade":3},{"Type":"FSD","Name":"Faster FSD Boot Sequence","Engineers":["Felicity Farseer","Elvira Martuuk"],"Ingredients":[{"Name":"Cadmium","Size":1,"Kind":0},{"Name":"Heat Exchangers","Size":1,"Kind":0},{"Name":"Hybrid Capacitors","Size":1,"Kind":0},{"Name":"Hardware Diagnostic Sensor","Size":1,"Kind":2}],"Favorite":false,"Ignored":false,"Grade":4},{"Type":"FSD","Name":"Faster FSD Boot Sequence","Engineers":["Felicity Farseer","Elvira Martuuk"],"Ingredients":[{"Name":"Electrochemical Arrays","Size":1,"Kind":0},{"Name":"Heat Vanes","Size":1,"Kind":0},{"Name":"Tellurium","Size":1,"Kind":0},{"Name":"Radiation Baffle","Size":1,"Kind":2}],"Favorite":false,"Ignored":false,"Grade":5},{"Type":"FSD","Name":"Increased FSD Range","Engineers":["Felicity Farseer","Elvira Martuuk","Professor Palin","Bris Dekker"],"Ingredients":[{"Name":"Atypical Disrupted Wake Echoes","Size":1,"Kind":1}],"Favorite":false,"Ignored":false,"Grade":1},{"Type":"FSD","Name":"Increased FSD Range","Engineers":["Felicity Farseer","Elvira Martuuk","Professor Palin","Bris Dekker"],"Ingredients":[{"Name":"Atypical Disrupted Wake Echoes","Size":1,"Kind":1},{"Name":"Chemical Processors","Size":1,"Kind":0},{"Name":"Praseodymium","Size":1,"Kind":2}],"Favorite":false,"Ignored":false,"Grade":2},{"Type":"FSD","Name":"Increased FSD Range","Engineers":["Felicity Farseer","Elvira Martuuk","Professor Palin","Bris Dekker"],"Ingredients":[{"Name":"Strange Wake Solutions","Size":1,"Kind":1},{"Name":"Chemical Processors","Size":1,"Kind":0},{"Name":"Phosphorus","Size":1,"Kind":0},{"Name":"Modular Terminals","Size":1,"Kind":2}],"Favorite":false,"Ignored":false,"Grade":3},{"Type":"FSD","Name":"Increased FSD Range","Engineers":["Felicity Farseer","Elvira Martuuk"],"Ingredients":[{"Name":"Eccentric Hyperspace Trajectories","Size":1,"Kind":1},{"Name":"Chemical Distillery","Size":1,"Kind":0},{"Name":"Manganese","Size":1,"Kind":0},{"Name":"Energy Grid Assembly","Size":1,"Kind":2}],"Favorite":false,"Ignored":false,"Grade":4},{"Type":"FSD","Name":"Increased FSD Range","Engineers":["Felicity Farseer","Elvira Martuuk"],"Ingredients":[{"Name":"Datamined Wake Exceptions","Size":1,"Kind":1},{"Name":"Chemical Manipulators","Size":1,"Kind":0},{"Name":"Arsenic","Size":1,"Kind":0},{"Name":"Magnetic Emitter Coil","Size":1,"Kind":2}],"Favorite":false,"Ignored":false,"Grade":5},{"Type":"FSD","Name":"Shielded FSD","Engineers":["Felicity Farseer","Elvira Martuuk","Professor Palin","Bris Dekker"],"Ingredients":[{"Name":"Nickel","Size":1,"Kind":0}],"Favorite":false,"Ignored":false,"Grade":1},{"Type":"FSD","Name":"Shielded FSD","Engineers":["Felicity Farseer","Elvira Martuuk","Professor Palin","Bris Dekker"],"Ingredients":[{"Name":"Carbon","Size":1,"Kind":0},{"Name":"Shielding Sensors","Size":1,"Kind":0},{"Name":"Insulating Membrane","Size":1,"Kind":2}],"Favorite":false,"Ignored":false,"Grade":2},{"Type":"FSD","Name":"Shielded FSD","Engineers":["Felicity Farseer","Elvira Martuuk","Professor Palin","Bris Dekker"],"Ingredients":[{"Name":"Carbon","Size":1,"Kind":0},{"Name":"Zinc","Size":1,"Kind":0},{"Name":"Shielding Sensors","Size":1,"Kind":0},{"Name":"Micro-Weave Cooling Hoses","Size":1,"Kind":2}],"Favorite":false,"Ignored":false,"Grade":3},{"Type":"FSD","Name":"Shielded FSD","Engineers":["Felicity Farseer","Elvira Martuuk"],"Ingredients":[{"Name":"Vanadium","Size":1,"Kind":0},{"Name":"High Density Composites","Size":1,"Kind":0},{"Name":"Compound Shielding","Size":1,"Kind":0},{"Name":"Bromellite","Size":1,"Kind":2}],"Favorite":false,"Ignored":false,"Grade":4},{"Type":"FSD","Name":"Shielded FSD","Engineers":["Felicity Farseer","Elvira Martuuk"],"Ingredients":[{"Name":"Tungsten","Size":1,"Kind":0},{"Name":"Proprietary Composites","Size":1,"Kind":0},{"Name":"Imperial Shielding","Size":1,"Kind":0},{"Name":"Radiation Baffle","Size":1,"Kind":2}],"Favorite":false,"Ignored":false,"Grade":5},{"Type":"Thrusters","Name":"Dirty Drive Tuning","Engineers":["Felicity Farseer","Elvira Martuuk","Professor Palin"],"Ingredients":[{"Name":"Specialised Legacy Firmware","Size":1,"Kind":1}],"Favorite":false,"Ignored":false,"Grade":1},{"Type":"Thrusters","Name":"Dirty Drive Tuning","Engineers":["Felicity Farseer","Elvira Martuuk","Professor Palin"],"Ingredients":[{"Name":"Specialised Legacy Firmware","Size":1,"Kind":1},{"Name":"Mechanical Equipment","Size":1,"Kind":0},{"Name":"Modular Terminals","Size":1,"Kind":2}],"Favorite":false,"Ignored":false,"Grade":2},{"Type":"Thrusters","Name":"Dirty Drive Tuning","Engineers":["Felicity Farseer","Professor Palin"],"Ingredients":[{"Name":"Specialised Legacy Firmware","Size":1,"Kind":1},{"Name":"Chromium","Size":1,"Kind":0},{"Name":"Mechanical Components","Size":1,"Kind":0},{"Name":"Micro-Weave Cooling Hoses","Size":1,"Kind":2}],"Favorite":false,"Ignored":false,"Grade":3},{"Type":"Thrusters","Name":"Dirty Drive Tuning","Engineers":["Professor Palin"],"Ingredients":[{"Name":"Modified Consumer Firmware","Size":1,"Kind":1},{"Name":"Selenium","Size":1,"Kind":0},{"Name":"Configurable Components","Size":1,"Kind":0},{"Name":"Heatsink Interlink","Size":1,"Kind":2}],"Favorite":false,"Ignored":false,"Grade":4},{"Type":"Thrusters","Name":"Dirty Drive Tuning","Engineers":["Professor Palin"],"Ingredients":[{"Name":"Cracked Industrial Firmware","Size":1,"Kind":1},{"Name":"Cadmium","Size":1,"Kind":0},{"Name":"Pharmaceutical Isolators","Size":1,"Kind":0},{"Name":"Exhaust Manifold","Size":1,"Kind":2}],"Favorite":false,"Ignored":false,"Grade":5},{"Type":"Thrusters","Name":"Drive Strengthening","Engineers":["Felicity Farseer","Elvira Martuuk","Professor Palin"],"Ingredients":[{"Name":"Carbon","Size":1,"Kind":0}],"Favorite":false,"Ignored":false,"Grade":1},{"Type":"Thrusters","Name":"Drive Strengthening","Engineers":["Felicity Farseer","Elvira Martuuk","Professor Palin"],"Ingredients":[{"Name":"Heat Conduction Wiring","Size":1,"Kind":0},{"Name":"Vanadium","Size":1,"Kind":0},{"Name":"Osmium","Size":1,"Kind":2}],"Favorite":false,"Ignored":false,"Grade":2},{"Type":"Thrusters","Name":"Drive Strengthening","Engineers":["Felicity Farseer","Professor Palin"],"Ingredients":[{"Name":"Heat Conduction Wiring","Size":1,"Kind":0},{"Name":"Vanadium","Size":1,"Kind":0},{"Name":"Shielding Sensors","Size":1,"Kind":0},{"Name":"CMM Composite","Size":1,"Kind":2}],"Favorite":false,"Ignored":false,"Grade":3},{"Type":"Thrusters","Name":"Drive Strengthening","Engineers":["Professor Palin"],"Ingredients":[{"Name":"Heat Dispersion Plate","Size":1,"Kind":0},{"Name":"High Density Composites","Size":1,"Kind":0},{"Name":"Compound Shielding","Size":1,"Kind":0},{"Name":"CMM Composite","Size":1,"Kind":2}],"Favorite":false,"Ignored":false,"Grade":4},{"Type":"Thrusters","Name":"Drive Strengthening","Engineers":["Professor Palin"],"Ingredients":[{"Name":"Heat Exchangers","Size":1,"Kind":0},{"Name":"Proprietary Composites","Size":1,"Kind":0},{"Name":"Imperial Shielding","Size":1,"Kind":0},{"Name":"Articulation Motors","Size":1,"Kind":2}],"Favorite":false,"Ignored":false,"Grade":5},{"Type":"Thrusters","Name":"Clean Drive Tuning","Engineers":["Felicity Farseer","Elvira Martuuk","Professor Palin"],"Ingredients":[{"Name":"Sulphur","Size":1,"Kind":0}],"Favorite":false,"Ignored":false,"Grade":1},{"Type":"Thrusters","Name":"Clean Drive Tuning","Engineers":["Felicity Farseer","Elvira Martuuk","Professor Palin"],"Ingredients":[{"Name":"Specialised Legacy Firmware","Size":1,"Kind":1},{"Name":"Conductive Components","Size":1,"Kind":0},{"Name":"Samarium","Size":1,"Kind":2}],"Favorite":false,"Ignored":false,"Grade":2},{"Type":"Thrusters","Name":"Clean Drive Tuning","Engineers":["Felicity Farseer","Professor Palin"],"Ingredients":[{"Name":"Specialised Legacy Firmware","Size":1,"Kind":1},{"Name":"Conductive Components","Size":1,"Kind":0},{"Name":"Unexpected Emission Data","Size":1,"Kind":1},{"Name":"Power Converter","Size":1,"Kind":2}],"Favorite":false,"Ignored":false,"Grade":3},{"Type":"Thrusters","Name":"Clean Drive Tuning","Engineers":["Professor Palin"],"Ingredients":[{"Name":"Modified Consumer Firmware","Size":1,"Kind":1},{"Name":"Conductive Ceramics","Size":1,"Kind":0},{"Name":"Decoded Emission Data","Size":1,"Kind":1},{"Name":"Power Converter","Size":1,"Kind":2}],"Favorite":false,"Ignored":false,"Grade":4},{"Type":"Thrusters","Name":"Clean Drive Tuning","Engineers":["Professor Palin"],"Ingredients":[{"Name":"Abnormal Compact Emission Data","Size":1,"Kind":1},{"Name":"Conductive Ceramics","Size":1,"Kind":0},{"Name":"Tin","Size":1,"Kind":0},{"Name":"Magnetic Emitter Coil","Size":1,"Kind":2}],"Favorite":false,"Ignored":false,"Grade":5},{"Type":"Booster (Shield)","Name":"Blast Resistant Shield Booster","Engineers":["Felicity Farseer","Lei Cheung","Didi Vatermann"],"Ingredients":[{"Name":"Iron","Size":1,"Kind":0}],"Favorite":false,"Ignored":false,"Grade":1},{"Type":"Booster (Shield)","Name":"Blast Resistant Shield Booster","Engineers":["Lei Cheung","Didi Vatermann"],"Ingredients":[{"Name":"Iron","Size":1,"Kind":0},{"Name":"Conductive Components","Size":1,"Kind":0},{"Name":"Micro Controllers","Size":1,"Kind":2}],"Favorite":false,"Ignored":false,"Grade":2},{"Type":"Booster (Shield)","Name":"Blast Resistant Shield Booster","Engineers":["Lei Cheung","Didi Vatermann"],"Ingredients":[{"Name":"Iron","Size":1,"Kind":0},{"Name":"Conductive Components","Size":1,"Kind":0},{"Name":"Focus Crystals","Size":1,"Kind":0},{"Name":"Magnetic Emitter Coil","Size":1,"Kind":2}],"Favorite":false,"Ignored":false,"Grade":3},{"Type":"Booster (Shield)","Name":"Heavy Duty Shield Booster","Engineers":["Felicity Farseer","Lei Cheung","Didi Vatermann"],"Ingredients":[{"Name":"Grid Resistors","Size":1,"Kind":0}],"Favorite":false,"Ignored":false,"Grade":1},{"Type":"Booster (Shield)","Name":"Heavy Duty Shield Booster","Engineers":["Lei Cheung","Didi Vatermann"],"Ingredients":[{"Name":"Distorted Shield Cycle Recordings","Size":1,"Kind":1},{"Name":"Hybrid Capacitors","Size":1,"Kind":0},{"Name":"CMM Composite","Size":1,"Kind":2}],"Favorite":false,"Ignored":false,"Grade":2},{"Type":"Booster (Shield)","Name":"Heavy Duty Shield Booster","Engineers":["Lei Cheung","Didi Vatermann"],"Ingredients":[{"Name":"Distorted Shield Cycle Recordings","Size":1,"Kind":1},{"Name":"Hybrid Capacitors","Size":1,"Kind":0},{"Name":"Niobium","Size":1,"Kind":0},{"Name":"Magnetic Emitter Coil","Size":1,"Kind":2}],"Favorite":false,"Ignored":false,"Grade":3},{"Type":"Booster (Shield)","Name":"Heavy Duty Shield Booster","Engineers":["Didi Vatermann"],"Ingredients":[{"Name":"Inconsistent Shield Soak Analysis","Size":1,"Kind":1},{"Name":"Electrochemical Arrays","Size":1,"Kind":0},{"Name":"Tin","Size":1,"Kind":0},{"Name":"Emergency Power Cells","Size":1,"Kind":2}],"Favorite":false,"Ignored":false,"Grade":4},{"Type":"Booster (Shield)","Name":"Heavy Duty Shield Booster","Engineers":["Didi Vatermann"],"Ingredients":[{"Name":"Untypical Shield Scans","Size":1,"Kind":1},{"Name":"Polymer Capacitors","Size":1,"Kind":0},{"Name":"Antimony","Size":1,"Kind":0},{"Name":"Emergency Power Cells","Size":1,"Kind":2}],"Favorite":false,"Ignored":false,"Grade":5},{"Type":"Booster (Shield)","Name":"Kinetic Resistant Shield Booster","Engineers":["Felicity Farseer","Lei Cheung","Didi Vatermann"],"Ingredients":[{"Name":"Iron","Size":1,"Kind":0}],"Favorite":false,"Ignored":false,"Grade":1},{"Type":"Booster (Shield)","Name":"Kinetic Resistant Shield Booster","Engineers":["Lei Cheung","Didi Vatermann"],"Ingredients":[{"Name":"Grid Resistors","Size":1,"Kind":0},{"Name":"Germanium","Size":1,"Kind":0},{"Name":"Micro Controllers","Size":1,"Kind":2}],"Favorite":false,"Ignored":false,"Grade":2},{"Type":"Booster (Shield)","Name":"Kinetic Resistant Shield Booster","Engineers":["Lei Cheung","Didi Vatermann"],"Ingredients":[{"Name":"Salvaged Alloys","Size":1,"Kind":0},{"Name":"Hybrid Capacitors","Size":1,"Kind":0},{"Name":"Focus Crystals","Size":1,"Kind":0},{"Name":"Magnetic Emitter Coil","Size":1,"Kind":2}],"Favorite":false,"Ignored":false,"Grade":3},{"Type":"Booster (Shield)","Name":"Resistance Augmented Shield Booster","Engineers":["Felicity Farseer","Lei Cheung","Didi Vatermann"],"Ingredients":[{"Name":"Phosphorus","Size":1,"Kind":0}],"Favorite":false,"Ignored":false,"Grade":1},{"Type":"Booster (Shield)","Name":"Resistance Augmented Shield Booster","Engineers":["Lei Cheung","Didi Vatermann"],"Ingredients":[{"Name":"Phosphorus","Size":1,"Kind":0},{"Name":"Conductive Components","Size":1,"Kind":0},{"Name":"Praseodymium","Size":1,"Kind":2}],"Favorite":false,"Ignored":false,"Grade":2},{"Type":"Booster (Shield)","Name":"Resistance Augmented Shield Booster","Engineers":["Lei Cheung","Didi Vatermann"],"Ingredients":[{"Name":"Phosphorus","Size":1,"Kind":0},{"Name":"Conductive Components","Size":1,"Kind":0},{"Name":"Focus Crystals","Size":1,"Kind":0},{"Name":"Modular Terminals","Size":1,"Kind":2}],"Favorite":false,"Ignored":false,"Grade":3},{"Type":"Booster (Shield)","Name":"Resistance Augmented Shield Booster","Engineers":["Didi Vatermann"],"Ingredients":[{"Name":"Manganese","Size":1,"Kind":0},{"Name":"Conductive Ceramics","Size":1,"Kind":0},{"Name":"Refined Focus Crystals","Size":1,"Kind":0},{"Name":"Radiation Baffle","Size":1,"Kind":2}],"Favorite":false,"Ignored":false,"Grade":4},{"Type":"Booster (Shield)","Name":"Resistance Augmented Shield Booster","Engineers":["Didi Vatermann"],"Ingredients":[{"Name":"Conductive Ceramics","Size":1,"Kind":0},{"Name":"Refined Focus Crystals","Size":1,"Kind":0},{"Name":"Imperial Shielding","Size":1,"Kind":0},{"Name":"Radiation Baffle","Size":1,"Kind":2}],"Favorite":false,"Ignored":false,"Grade":5},{"Type":"Booster (Shield)","Name":"Thermal Resistant Shield Booster","Engineers":["Felicity Farseer","Lei Cheung","Didi Vatermann"],"Ingredients":[{"Name":"Iron","Size":1,"Kind":0}],"Favorite":false,"Ignored":false,"Grade":1},{"Type":"Booster (Shield)","Name":"Thermal Resistant Shield Booster","Engineers":["Lei Cheung","Didi Vatermann"],"Ingredients":[{"Name":"Heat Conduction Wiring","Size":1,"Kind":0},{"Name":"Germanium","Size":1,"Kind":0},{"Name":"Micro Controllers","Size":1,"Kind":2}],"Favorite":false,"Ignored":false,"Grade":2},{"Type":"Booster (Shield)","Name":"Thermal Resistant Shield Booster","Engineers":["Lei Cheung","Didi Vatermann"],"Ingredients":[{"Name":"Heat Conduction Wiring","Size":1,"Kind":0},{"Name":"Heat Dispersion Plate","Size":1,"Kind":0},{"Name":"Focus Crystals","Size":1,"Kind":0},{"Name":"Magnetic Emitter Coil","Size":1,"Kind":2}],"Favorite":false,"Ignored":false,"Grade":3},{"Type":"Power Plant","Name":"Armoured Power Plant","Engineers":["Felicity Farseer","Marco Qwent","Hera Tani"],"Ingredients":[{"Name":"Worn Shield Emitters","Size":1,"Kind":0}],"Favorite":false,"Ignored":false,"Grade":1},{"Type":"Power Plant","Name":"Armoured Power Plant","Engineers":["Marco Qwent","Hera Tani"],"Ingredients":[{"Name":"Carbon","Size":1,"Kind":0},{"Name":"Shield Emitters","Size":1,"Kind":0},{"Name":"Osmium","Size":1,"Kind":2}],"Favorite":false,"Ignored":false,"Grade":2},{"Type":"Power Plant","Name":"Armoured Power Plant","Engineers":["Marco Qwent","Hera Tani"],"Ingredients":[{"Name":"Carbon","Size":1,"Kind":0},{"Name":"Shield Emitters","Size":1,"Kind":0},{"Name":"High Density Composites","Size":1,"Kind":0},{"Name":"CMM Composite","Size":1,"Kind":2}],"Favorite":false,"Ignored":false,"Grade":3},{"Type":"Power Plant","Name":"Armoured Power Plant","Engineers":["Marco Qwent","Hera Tani"],"Ingredients":[{"Name":"Vanadium","Size":1,"Kind":0},{"Name":"Shielding Sensors","Size":1,"Kind":0},{"Name":"Proprietary Composites","Size":1,"Kind":0},{"Name":"CMM Composite","Size":1,"Kind":2}],"Favorite":false,"Ignored":false,"Grade":4},{"Type":"Power Plant","Name":"Armoured Power Plant","Engineers":["Hera Tani"],"Ingredients":[{"Name":"Tungsten","Size":1,"Kind":0},{"Name":"Compound Shielding","Size":1,"Kind":0},{"Name":"Core Dynamics Composites","Size":1,"Kind":0},{"Name":"Reinforced Mounting Plate","Size":1,"Kind":2}],"Favorite":false,"Ignored":false,"Grade":5},{"Type":"Power Plant","Name":"Overcharged Power Plant","Engineers":["Felicity Farseer","Marco Qwent","Hera Tani"],"Ingredients":[{"Name":"Sulphur","Size":1,"Kind":0}],"Favorite":false,"Ignored":false,"Grade":1},{"Type":"Power Plant","Name":"Overcharged Power Plant","Engineers":["Marco Qwent","Hera Tani"],"Ingredients":[{"Name":"Heat Conduction Wiring","Size":1,"Kind":0},{"Name":"Conductive Components","Size":1,"Kind":0},{"Name":"Platinum","Size":1,"Kind":2}],"Favorite":false,"Ignored":false,"Grade":2},{"Type":"Power Plant","Name":"Overcharged Power Plant","Engineers":["Marco Qwent","Hera Tani"],"Ingredients":[{"Name":"Heat Conduction Wiring","Size":1,"Kind":0},{"Name":"Conductive Components","Size":1,"Kind":0},{"Name":"Selenium","Size":1,"Kind":0},{"Name":"Emergency Power Cells","Size":1,"Kind":2}],"Favorite":false,"Ignored":false,"Grade":3},{"Type":"Power Plant","Name":"Overcharged Power Plant","Engineers":["Marco Qwent","Hera Tani"],"Ingredients":[{"Name":"Heat Dispersion Plate","Size":1,"Kind":0},{"Name":"Conductive Ceramics","Size":1,"Kind":0},{"Name":"Cadmium","Size":1,"Kind":0},{"Name":"Energy Grid Assembly","Size":1,"Kind":2}],"Favorite":false,"Ignored":false,"Grade":4},{"Type":"Power Plant","Name":"Overcharged Power Plant","Engineers":["Hera Tani"],"Ingredients":[{"Name":"Conductive Ceramics","Size":1,"Kind":0},{"Name":"Tellurium","Size":1,"Kind":0},{"Name":"Chemical Manipulators","Size":1,"Kind":0},{"Name":"Energy Grid Assembly","Size":1,"Kind":2}],"Favorite":false,"Ignored":false,"Grade":5},{"Type":"Power Plant","Name":"Low Emissions Power Plant","Engineers":["Felicity Farseer","Marco Qwent","Hera Tani"],"Ingredients":[{"Name":"Iron","Size":1,"Kind":0}],"Favorite":false,"Ignored":false,"Grade":1},{"Type":"Power Plant","Name":"Low Emissions Power Plant","Engineers":["Marco Qwent","Hera Tani"],"Ingredients":[{"Name":"Iron","Size":1,"Kind":0},{"Name":"Irregular Emission Data","Size":1,"Kind":1},{"Name":"Micro-Weave Cooling Hoses","Size":1,"Kind":2}],"Favorite":false,"Ignored":false,"Grade":2},{"Type":"Power Plant","Name":"Low Emissions Power Plant","Engineers":["Marco Qwent","Hera Tani"],"Ingredients":[{"Name":"Iron","Size":1,"Kind":0},{"Name":"Irregular Emission Data","Size":1,"Kind":1},{"Name":"Heat Exchangers","Size":1,"Kind":0},{"Name":"Samarium","Size":1,"Kind":2}],"Favorite":false,"Ignored":false,"Grade":3},{"Type":"Interdictor","Name":"Expanded FSD Interdictor Capture Arc","Engineers":["Felicity Farseer"],"Ingredients":[{"Name":"Mechanical Scrap","Size":1,"Kind":0}],"Favorite":false,"Ignored":false,"Grade":1},{"Type":"Interdictor","Name":"Longer Range FSD Interdictor","Engineers":["Felicity Farseer"],"Ingredients":[{"Name":"Unusual Encrypted Files","Size":1,"Kind":1}],"Favorite":false,"Ignored":false,"Grade":1},{"Type":"Cell Banks","Name":"Rapid Charge Shield Cell Bank","Engineers":["Elvira Martuuk"],"Ingredients":[{"Name":"Sulphur","Size":1,"Kind":0}],"Favorite":false,"Ignored":false,"Grade":1},{"Type":"Cell Banks","Name":"Specialised Shield Cell Bank","Engineers":["Elvira Martuuk"],"Ingredients":[{"Name":"Specialised Legacy Firmware","Size":1,"Kind":1}],"Favorite":false,"Ignored":false,"Grade":1},{"Type":"Shield Generator","Name":"Kinetic Resistant Shields","Engineers":["Elvira Martuuk","Lei Cheung","Didi Vatermann"],"Ingredients":[{"Name":"Distorted Shield Cycle Recordings","Size":1,"Kind":1}],"Favorite":false,"Ignored":false,"Grade":1},{"Type":"Shield Generator","Name":"Kinetic Resistant Shields","Engineers":["Elvira Martuuk","Lei Cheung","Didi Vatermann"],"Ingredients":[{"Name":"Distorted Shield Cycle Recordings","Size":1,"Kind":1},{"Name":"Modified Consumer Firmware","Size":1,"Kind":1},{"Name":"Micro-Weave Cooling Hoses","Size":1,"Kind":2}],"Favorite":false,"Ignored":false,"Grade":2},{"Type":"Shield Generator","Name":"Kinetic Resistant Shields","Engineers":["Elvira Martuuk","Lei Cheung","Didi Vatermann"],"Ingredients":[{"Name":"Distorted Shield Cycle Recordings","Size":1,"Kind":1},{"Name":"Modified Consumer Firmware","Size":1,"Kind":1},{"Name":"Selenium","Size":1,"Kind":0},{"Name":"Micro-Weave Cooling Hoses","Size":1,"Kind":2}],"Favorite":false,"Ignored":false,"Grade":3},{"Type":"Shield Generator","Name":"Kinetic Resistant Shields","Engineers":["Lei Cheung"],"Ingredients":[{"Name":"Inconsistent Shield Soak Analysis","Size":1,"Kind":1},{"Name":"Focus Crystals","Size":1,"Kind":0},{"Name":"Ion Distributor","Size":1,"Kind":2},{"Name":"Mercury","Size":1,"Kind":0}],"Favorite":false,"Ignored":false,"Grade":4},{"Type":"Shield Generator","Name":"Kinetic Resistant Shields","Engineers":["Lei Cheung"],"Ingredients":[{"Name":"Untypical Shield Scans","Size":1,"Kind":1},{"Name":"Refined Focus Crystals","Size":1,"Kind":0},{"Name":"Ion Distributor","Size":1,"Kind":2},{"Name":"Ruthenium","Size":1,"Kind":0}],"Favorite":false,"Ignored":false,"Grade":5},{"Type":"Shield Generator","Name":"Enhanced, Low Power Shields","Engineers":["Elvira Martuuk","Lei Cheung","Didi Vatermann"],"Ingredients":[{"Name":"Distorted Shield Cycle Recordings","Size":1,"Kind":1}],"Favorite":false,"Ignored":false,"Grade":1},{"Type":"Shield Generator","Name":"Enhanced, Low Power Shields","Engineers":["Elvira Martuuk","Lei Cheung","Didi Vatermann"],"Ingredients":[{"Name":"Distorted Shield Cycle Recordings","Size":1,"Kind":1},{"Name":"Germanium","Size":1,"Kind":0},{"Name":"Micro Controllers","Size":1,"Kind":2}],"Favorite":false,"Ignored":false,"Grade":2},{"Type":"Shield Generator","Name":"Enhanced, Low Power Shields","Engineers":["Elvira Martuuk","Lei Cheung","Didi Vatermann"],"Ingredients":[{"Name":"Distorted Shield Cycle Recordings","Size":1,"Kind":1},{"Name":"Germanium","Size":1,"Kind":0},{"Name":"Precipitated Alloys","Size":1,"Kind":0},{"Name":"Power Transfer Bus","Size":1,"Kind":2}],"Favorite":false,"Ignored":false,"Grade":3},{"Type":"Shield Generator","Name":"Enhanced, Low Power Shields","Engineers":["Lei Cheung"],"Ingredients":[{"Name":"Inconsistent Shield Soak Analysis","Size":1,"Kind":1},{"Name":"Niobium","Size":1,"Kind":0},{"Name":"Thermic Alloys","Size":1,"Kind":0},{"Name":"Nanobreakers","Size":1,"Kind":2}],"Favorite":false,"Ignored":false,"Grade":4},{"Type":"Shield Generator","Name":"Enhanced, Low Power Shields","Engineers":["Lei Cheung"],"Ingredients":[{"Name":"Untypical Shield Scans","Size":1,"Kind":1},{"Name":"Tin","Size":1,"Kind":0},{"Name":"Military Grade Alloys","Size":1,"Kind":0},{"Name":"Platinum","Size":1,"Kind":2}],"Favorite":false,"Ignored":false,"Grade":5},{"Type":"Shield Generator","Name":"Reinforced Shields","Engineers":["Elvira Martuuk","Lei Cheung","Didi Vatermann"],"Ingredients":[{"Name":"Phosphorus","Size":1,"Kind":0}],"Favorite":false,"Ignored":false,"Grade":1},{"Type":"Shield Generator","Name":"Reinforced Shields","Engineers":["Elvira Martuuk","Lei Cheung","Didi Vatermann"],"Ingredients":[{"Name":"Phosphorus","Size":1,"Kind":0},{"Name":"Conductive Components","Size":1,"Kind":0},{"Name":"Modular Terminals","Size":1,"Kind":2}],"Favorite":false,"Ignored":false,"Grade":2},{"Type":"Shield Generator","Name":"Reinforced Shields","Engineers":["Elvira Martuuk","Lei Cheung","Didi Vatermann"],"Ingredients":[{"Name":"Phosphorus","Size":1,"Kind":0},{"Name":"Conductive Components","Size":1,"Kind":0},{"Name":"Mechanical Components","Size":1,"Kind":0},{"Name":"Magnetic Emitter Coil","Size":1,"Kind":2}],"Favorite":false,"Ignored":false,"Grade":3},{"Type":"Shield Generator","Name":"Reinforced Shields","Engineers":["Lei Cheung"],"Ingredients":[{"Name":"Manganese","Size":1,"Kind":0},{"Name":"Conductive Ceramics","Size":1,"Kind":0},{"Name":"Configurable Components","Size":1,"Kind":0},{"Name":"Magnetic Emitter Coil","Size":1,"Kind":2}],"Favorite":false,"Ignored":false,"Grade":4},{"Type":"Shield Generator","Name":"Reinforced Shields","Engineers":["Lei Cheung"],"Ingredients":[{"Name":"Arsenic","Size":1,"Kind":0},{"Name":"Conductive Polymers","Size":1,"Kind":0},{"Name":"Improvised Components","Size":1,"Kind":0},{"Name":"Ion Distributor","Size":1,"Kind":2}],"Favorite":false,"Ignored":false,"Grade":5},{"Type":"Shield Generator","Name":"Thermal Resistant Shields","Engineers":["Elvira Martuuk","Lei Cheung","Didi Vatermann"],"Ingredients":[{"Name":"Distorted Shield Cycle Recordings","Size":1,"Kind":1}],"Favorite":false,"Ignored":false,"Grade":1},{"Type":"Shield Generator","Name":"Thermal Resistant Shields","Engineers":["Elvira Martuuk","Lei Cheung","Didi Vatermann"],"Ingredients":[{"Name":"Distorted Shield Cycle Recordings","Size":1,"Kind":1},{"Name":"Germanium","Size":1,"Kind":0},{"Name":"Micro-Weave Cooling Hoses","Size":1,"Kind":2}],"Favorite":false,"Ignored":false,"Grade":2},{"Type":"Shield Generator","Name":"Thermal Resistant Shields","Engineers":["Elvira Martuuk","Lei Cheung","Didi Vatermann"],"Ingredients":[{"Name":"Distorted Shield Cycle Recordings","Size":1,"Kind":1},{"Name":"Germanium","Size":1,"Kind":0},{"Name":"Selenium","Size":1,"Kind":0},{"Name":"Micro-Weave Cooling Hoses","Size":1,"Kind":2}],"Favorite":false,"Ignored":false,"Grade":3},{"Type":"Shield Generator","Name":"Thermal Resistant Shields","Engineers":["Lei Cheung"],"Ingredients":[{"Name":"Inconsistent Shield Soak Analysis","Size":1,"Kind":1},{"Name":"Focus Crystals","Size":1,"Kind":0},{"Name":"Mercury","Size":1,"Kind":0},{"Name":"Ion Distributor","Size":1,"Kind":2}],"Favorite":false,"Ignored":false,"Grade":4},{"Type":"Shield Generator","Name":"Thermal Resistant Shields","Engineers":["Lei Cheung"],"Ingredients":[{"Name":"Untypical Shield Scans","Size":1,"Kind":1},{"Name":"Refined Focus Crystals","Size":1,"Kind":0},{"Name":"Ruthenium","Size":1,"Kind":0},{"Name":"Ion Distributor","Size":1,"Kind":2}],"Favorite":false,"Ignored":false,"Grade":5},{"Type":"Hull Reinforcement","Name":"Lightweight Hull Reinforcement","Engineers":["Liz Ryder"],"Ingredients":[{"Name":"Iron","Size":1,"Kind":0}],"Favorite":false,"Ignored":false,"Grade":1},{"Type":"Hull Reinforcement","Name":"Blast Resistant Hull Reinforcement","Engineers":["Liz Ryder"],"Ingredients":[{"Name":"Nickel","Size":1,"Kind":0}],"Favorite":false,"Ignored":false,"Grade":1},{"Type":"Hull Reinforcement","Name":"Heavy Duty Hull Reinforcement","Engineers":["Liz Ryder"],"Ingredients":[{"Name":"Carbon","Size":1,"Kind":0}],"Favorite":false,"Ignored":false,"Grade":1},{"Type":"Hull Reinforcement","Name":"Kinetic Resistant Hull Reinforcement","Engineers":["Liz Ryder"],"Ingredients":[{"Name":"Nickel","Size":1,"Kind":0}],"Favorite":false,"Ignored":false,"Grade":1},{"Type":"Hull Reinforcement","Name":"Thermal Resistant Hull Reinforcement","Engineers":["Liz Ryder"],"Ingredients":[{"Name":"Heat Conduction Wiring","Size":1,"Kind":0}],"Favorite":false,"Ignored":false,"Grade":1},{"Type":"Mine Launcher","Name":"High Capacity Magazine","Engineers":["Liz Ryder","Juri Ishmaak"],"Ingredients":[{"Name":"Mechanical Scrap","Size":1,"Kind":0}],"Favorite":false,"Ignored":false,"Grade":1},{"Type":"Mine Launcher","Name":"High Capacity Magazine","Engineers":["Liz Ryder","Juri Ishmaak"],"Ingredients":[{"Name":"Mechanical Scrap","Size":1,"Kind":0},{"Name":"Vanadium","Size":1,"Kind":0},{"Name":"CMM Composite","Size":1,"Kind":2}],"Favorite":false,"Ignored":false,"Grade":2},{"Type":"Mine Launcher","Name":"High Capacity Magazine","Engineers":["Liz Ryder","Juri Ishmaak"],"Ingredients":[{"Name":"Mechanical Scrap","Size":1,"Kind":0},{"Name":"Vanadium","Size":1,"Kind":0},{"Name":"Niobium","Size":1,"Kind":0},{"Name":"Reinforced Mounting Plate","Size":1,"Kind":2}],"Favorite":false,"Ignored":false,"Grade":3},{"Type":"Mine Launcher","Name":"High Capacity Magazine","Engineers":["Juri Ishmaak"],"Ingredients":[{"Name":"Mechanical Equipment","Size":1,"Kind":0},{"Name":"High Density Composites","Size":1,"Kind":0},{"Name":"Tin","Size":1,"Kind":0},{"Name":"Reinforced Mounting Plate","Size":1,"Kind":2}],"Favorite":false,"Ignored":false,"Grade":4},{"Type":"Mine Launcher","Name":"Rapid Fire Modification","Engineers":["Liz Ryder","Juri Ishmaak"],"Ingredients":[{"Name":"Mechanical Scrap","Size":1,"Kind":0}],"Favorite":false,"Ignored":false,"Grade":1},{"Type":"Mine Launcher","Name":"Rapid Fire Modification","Engineers":["Liz Ryder","Juri Ishmaak"],"Ingredients":[{"Name":"Mechanical Scrap","Size":1,"Kind":0},{"Name":"Heat Dispersion Plate","Size":1,"Kind":0},{"Name":"HN Shock Mount","Size":1,"Kind":2}],"Favorite":false,"Ignored":false,"Grade":2},{"Type":"Mine Launcher","Name":"Rapid Fire Modification","Engineers":["Liz Ryder","Juri Ishmaak"],"Ingredients":[{"Name":"Specialised Legacy Firmware","Size":1,"Kind":1},{"Name":"Mechanical Equipment","Size":1,"Kind":0},{"Name":"Precipitated Alloys","Size":1,"Kind":0},{"Name":"Osmium","Size":1,"Kind":2}],"Favorite":false,"Ignored":false,"Grade":3},{"Type":"Mine Launcher","Name":"Rapid Fire Modification","Engineers":["Juri Ishmaak"],"Ingredients":[{"Name":"Modified Consumer Firmware","Size":1,"Kind":1},{"Name":"Mechanical Components","Size":1,"Kind":0},{"Name":"Thermic Alloys","Size":1,"Kind":0},{"Name":"Telemetry Suite","Size":1,"Kind":2}],"Favorite":false,"Ignored":false,"Grade":4},{"Type":"Mine Launcher","Name":"Light Weight Mount","Engineers":["Liz Ryder","Juri Ishmaak"],"Ingredients":[{"Name":"Phosphorus","Size":1,"Kind":0}],"Favorite":false,"Ignored":false,"Grade":1},{"Type":"Mine Launcher","Name":"Light Weight Mount","Engineers":["Liz Ryder","Juri Ishmaak"],"Ingredients":[{"Name":"Salvaged Alloys","Size":1,"Kind":0},{"Name":"Manganese","Size":1,"Kind":0},{"Name":"CMM Composite","Size":1,"Kind":2}],"Favorite":false,"Ignored":false,"Grade":2},{"Type":"Mine Launcher","Name":"Light Weight Mount","Engineers":["Liz Ryder","Juri Ishmaak"],"Ingredients":[{"Name":"Salvaged Alloys","Size":1,"Kind":0},{"Name":"Manganese","Size":1,"Kind":0},{"Name":"Conductive Ceramics","Size":1,"Kind":0},{"Name":"CMM Composite","Size":1,"Kind":2}],"Favorite":false,"Ignored":false,"Grade":3},{"Type":"Mine Launcher","Name":"Light Weight Mount","Engineers":["Juri Ishmaak"],"Ingredients":[{"Name":"Conductive Components","Size":1,"Kind":0},{"Name":"Proto Light Alloys","Size":1,"Kind":0},{"Name":"Magnetic Emitter Coil","Size":1,"Kind":2},{"Name":"Phase Alloys","Size":1,"Kind":0}],"Favorite":false,"Ignored":false,"Grade":4},{"Type":"Mine Launcher","Name":"Sturdy Mount","Engineers":["Liz Ryder","Juri Ishmaak"],"Ingredients":[{"Name":"Nickel","Size":1,"Kind":0}],"Favorite":false,"Ignored":false,"Grade":1},{"Type":"Mine Launcher","Name":"Sturdy Mount","Engineers":["Liz Ryder","Juri Ishmaak"],"Ingredients":[{"Name":"Nickel","Size":1,"Kind":0},{"Name":"Shield Emitters","Size":1,"Kind":0},{"Name":"HN Shock Mount","Size":1,"Kind":2}],"Favorite":false,"Ignored":false,"Grade":2},{"Type":"Mine Launcher","Name":"Sturdy Mount","Engineers":["Liz Ryder","Juri Ishmaak"],"Ingredients":[{"Name":"Nickel","Size":1,"Kind":0},{"Name":"Shield Emitters","Size":1,"Kind":0},{"Name":"Tungsten","Size":1,"Kind":0},{"Name":"Osmium","Size":1,"Kind":2}],"Favorite":false,"Ignored":false,"Grade":3},{"Type":"Mine Launcher","Name":"Sturdy Mount","Engineers":["Juri Ishmaak"],"Ingredients":[{"Name":"Zinc","Size":1,"Kind":0},{"Name":"Molybdenum","Size":1,"Kind":0},{"Name":"Tungsten","Size":1,"Kind":0},{"Name":"Osmium","Size":1,"Kind":2}],"Favorite":false,"Ignored":false,"Grade":4},{"Type":"Seeker Missile Rack","Name":"High Capacity Magazine","Engineers":["Liz Ryder","Juri Ishmaak"],"Ingredients":[{"Name":"Mechanical Scrap","Size":1,"Kind":0}],"Favorite":false,"Ignored":false,"Grade":1},{"Type":"Seeker Missile Rack","Name":"High Capacity Magazine","Engineers":["Liz Ryder","Juri Ishmaak"],"Ingredients":[{"Name":"Mechanical Scrap","Size":1,"Kind":0},{"Name":"Vanadium","Size":1,"Kind":0},{"Name":"CMM Composite","Size":1,"Kind":2}],"Favorite":false,"Ignored":false,"Grade":2},{"Type":"Seeker Missile Rack","Name":"High Capacity Magazine","Engineers":["Liz Ryder","Juri Ishmaak"],"Ingredients":[{"Name":"Mechanical Scrap","Size":1,"Kind":0},{"Name":"Vanadium","Size":1,"Kind":0},{"Name":"Niobium","Size":1,"Kind":0},{"Name":"Reinforced Mounting Plate","Size":1,"Kind":2}],"Favorite":false,"Ignored":false,"Grade":3},{"Type":"Seeker Missile Rack","Name":"High Capacity Magazine","Engineers":["Liz Ryder"],"Ingredients":[{"Name":"Mechanical Equipment","Size":1,"Kind":0},{"Name":"High Density Composites","Size":1,"Kind":0},{"Name":"Tin","Size":1,"Kind":0},{"Name":"Reinforced Mounting Plate","Size":1,"Kind":2}],"Favorite":false,"Ignored":false,"Grade":4},{"Type":"Seeker Missile Rack","Name":"Rapid Fire Modification","Engineers":["Liz Ryder","Juri Ishmaak"],"Ingredients":[{"Name":"Mechanical Scrap","Size":1,"Kind":0}],"Favorite":false,"Ignored":false,"Grade":1},{"Type":"Seeker Missile Rack","Name":"Rapid Fire Modification","Engineers":["Liz Ryder","Juri Ishmaak"],"Ingredients":[{"Name":"Mechanical Scrap","Size":1,"Kind":0},{"Name":"Heat Dispersion Plate","Size":1,"Kind":0},{"Name":"HN Shock Mount","Size":1,"Kind":2}],"Favorite":false,"Ignored":false,"Grade":2},{"Type":"Seeker Missile Rack","Name":"Rapid Fire Modification","Engineers":["Liz Ryder","Juri Ishmaak"],"Ingredients":[{"Name":"Specialised Legacy Firmware","Size":1,"Kind":1},{"Name":"Mechanical Equipment","Size":1,"Kind":0},{"Name":"Precipitated Alloys","Size":1,"Kind":0},{"Name":"Osmium","Size":1,"Kind":2}],"Favorite":false,"Ignored":false,"Grade":3},{"Type":"Seeker Missile Rack","Name":"Rapid Fire Modification","Engineers":["Liz Ryder"],"Ingredients":[{"Name":"Modified Consumer Firmware","Size":1,"Kind":1},{"Name":"Mechanical Components","Size":1,"Kind":0},{"Name":"Thermic Alloys","Size":1,"Kind":0},{"Name":"Telemetry Suite","Size":1,"Kind":2}],"Favorite":false,"Ignored":false,"Grade":4},{"Type":"Seeker Missile Rack","Name":"Light Weight Mount","Engineers":["Liz Ryder","Juri Ishmaak"],"Ingredients":[{"Name":"Phosphorus","Size":1,"Kind":0}],"Favorite":false,"Ignored":false,"Grade":1},{"Type":"Seeker Missile Rack","Name":"Light Weight Mount","Engineers":["Liz Ryder","Juri Ishmaak"],"Ingredients":[{"Name":"Salvaged Alloys","Size":1,"Kind":0},{"Name":"Manganese","Size":1,"Kind":0},{"Name":"CMM Composite","Size":1,"Kind":2}],"Favorite":false,"Ignored":false,"Grade":2},{"Type":"Seeker Missile Rack","Name":"Light Weight Mount","Engineers":["Liz Ryder","Juri Ishmaak"],"Ingredients":[{"Name":"Salvaged Alloys","Size":1,"Kind":0},{"Name":"Manganese","Size":1,"Kind":0},{"Name":"Conductive Ceramics","Size":1,"Kind":0},{"Name":"CMM Composite","Size":1,"Kind":2}],"Favorite":false,"Ignored":false,"Grade":3},{"Type":"Seeker Missile Rack","Name":"Light Weight Mount","Engineers":["Liz Ryder"],"Ingredients":[{"Name":"Conductive Components","Size":1,"Kind":0},{"Name":"Proto Light Alloys","Size":1,"Kind":0},{"Name":"Magnetic Emitter Coil","Size":1,"Kind":2},{"Name":"Phase Alloys","Size":1,"Kind":0}],"Favorite":false,"Ignored":false,"Grade":4},{"Type":"Seeker Missile Rack","Name":"Sturdy Mount","Engineers":["Liz Ryder","Juri Ishmaak"],"Ingredients":[{"Name":"Nickel","Size":1,"Kind":0}],"Favorite":false,"Ignored":false,"Grade":1},{"Type":"Seeker Missile Rack","Name":"Sturdy Mount","Engineers":["Liz Ryder","Juri Ishmaak"],"Ingredients":[{"Name":"Nickel","Size":1,"Kind":0},{"Name":"Shield Emitters","Size":1,"Kind":0},{"Name":"HN Shock Mount","Size":1,"Kind":2}],"Favorite":false,"Ignored":false,"Grade":2},{"Type":"Seeker Missile Rack","Name":"Sturdy Mount","Engineers":["Liz Ryder","Juri Ishmaak"],"Ingredients":[{"Name":"Nickel","Size":1,"Kind":0},{"Name":"Shield Emitters","Size":1,"Kind":0},{"Name":"Tungsten","Size":1,"Kind":0},{"Name":"Osmium","Size":1,"Kind":2}],"Favorite":false,"Ignored":false,"Grade":3},{"Type":"Seeker Missile Rack","Name":"Sturdy Mount","Engineers":["Liz Ryder"],"Ingredients":[{"Name":"Zinc","Size":1,"Kind":0},{"Name":"Molybdenum","Size":1,"Kind":0},{"Name":"Tungsten","Size":1,"Kind":0},{"Name":"Osmium","Size":1,"Kind":2}],"Favorite":false,"Ignored":false,"Grade":4},{"Type":"Armour","Name":"Lightweight Armour","Engineers":["Liz Ryder","Selene Jean"],"Ingredients":[{"Name":"Iron","Size":1,"Kind":0}],"Favorite":false,"Ignored":false,"Grade":1},{"Type":"Armour","Name":"Lightweight Armour","Engineers":["Selene Jean"],"Ingredients":[{"Name":"Iron","Size":1,"Kind":0},{"Name":"Conductive Components","Size":1,"Kind":0},{"Name":"HN Shock Mount","Size":1,"Kind":2}],"Favorite":false,"Ignored":false,"Grade":2},{"Type":"Armour","Name":"Lightweight Armour","Engineers":["Selene Jean"],"Ingredients":[{"Name":"Iron","Size":1,"Kind":0},{"Name":"Conductive Components","Size":1,"Kind":0},{"Name":"High Density Composites","Size":1,"Kind":0},{"Name":"Telemetry Suite","Size":1,"Kind":2}],"Favorite":false,"Ignored":false,"Grade":3},{"Type":"Armour","Name":"Blast Resistant Armour","Engineers":["Liz Ryder","Selene Jean"],"Ingredients":[{"Name":"Nickel","Size":1,"Kind":0}],"Favorite":false,"Ignored":false,"Grade":1},{"Type":"Armour","Name":"Blast Resistant Armour","Engineers":["Selene Jean"],"Ingredients":[{"Name":"Carbon","Size":1,"Kind":0},{"Name":"Zinc","Size":1,"Kind":0},{"Name":"CMM Composite","Size":1,"Kind":2}],"Favorite":false,"Ignored":false,"Grade":2},{"Type":"Armour","Name":"Blast Resistant Armour","Engineers":["Selene Jean"],"Ingredients":[{"Name":"Vanadium","Size":1,"Kind":0},{"Name":"Salvaged Alloys","Size":1,"Kind":0},{"Name":"Zirconium","Size":1,"Kind":0},{"Name":"Osmium","Size":1,"Kind":2}],"Favorite":false,"Ignored":false,"Grade":3},{"Type":"Armour","Name":"Heavy Duty Armour","Engineers":["Liz Ryder","Selene Jean"],"Ingredients":[{"Name":"Carbon","Size":1,"Kind":0}],"Favorite":false,"Ignored":false,"Grade":1},{"Type":"Armour","Name":"Heavy Duty Armour","Engineers":["Selene Jean"],"Ingredients":[{"Name":"Carbon","Size":1,"Kind":0},{"Name":"Shield Emitters","Size":1,"Kind":0},{"Name":"Articulation Motors","Size":1,"Kind":2}],"Favorite":false,"Ignored":false,"Grade":2},{"Type":"Armour","Name":"Heavy Duty Armour","Engineers":["Selene Jean"],"Ingredients":[{"Name":"Carbon","Size":1,"Kind":0},{"Name":"Shield Emitters","Size":1,"Kind":0},{"Name":"High Density Composites","Size":1,"Kind":0},{"Name":"Reinforced Mounting Plate","Size":1,"Kind":2}],"Favorite":false,"Ignored":false,"Grade":3},{"Type":"Armour","Name":"Heavy Duty Armour","Engineers":["Selene Jean"],"Ingredients":[{"Name":"Vanadium","Size":1,"Kind":0},{"Name":"Shielding Sensors","Size":1,"Kind":0},{"Name":"Proprietary Composites","Size":1,"Kind":0},{"Name":"Reinforced Mounting Plate","Size":1,"Kind":2}],"Favorite":false,"Ignored":false,"Grade":4},{"Type":"Armour","Name":"Heavy Duty Armour","Engineers":["Selene Jean"],"Ingredients":[{"Name":"Tungsten","Size":1,"Kind":0},{"Name":"Compound Shielding","Size":1,"Kind":0},{"Name":"Core Dynamics Composites","Size":1,"Kind":0},{"Name":"Reinforced Mounting Plate","Size":1,"Kind":2}],"Favorite":false,"Ignored":false,"Grade":5},{"Type":"Armour","Name":"Kinetic Resistant Armour","Engineers":["Liz Ryder","Selene Jean"],"Ingredients":[{"Name":"Nickel","Size":1,"Kind":0}],"Favorite":false,"Ignored":false,"Grade":1},{"Type":"Armour","Name":"Kinetic Resistant Armour","Engineers":["Selene Jean"],"Ingredients":[{"Name":"Nickel","Size":1,"Kind":0},{"Name":"Vanadium","Size":1,"Kind":0},{"Name":"Micro-Weave Cooling Hoses","Size":1,"Kind":2}],"Favorite":false,"Ignored":false,"Grade":2},{"Type":"Armour","Name":"Kinetic Resistant Armour","Engineers":["Selene Jean"],"Ingredients":[{"Name":"Salvaged Alloys","Size":1,"Kind":0},{"Name":"Vanadium","Size":1,"Kind":0},{"Name":"High Density Composites","Size":1,"Kind":0},{"Name":"CMM Composite","Size":1,"Kind":2}],"Favorite":false,"Ignored":false,"Grade":3},{"Type":"Armour","Name":"Thermal Resistant Armour","Engineers":["Liz Ryder","Selene Jean"],"Ingredients":[{"Name":"Heat Conduction Wiring","Size":1,"Kind":0}],"Favorite":false,"Ignored":false,"Grade":1},{"Type":"Armour","Name":"Thermal Resistant Armour","Engineers":["Selene Jean"],"Ingredients":[{"Name":"Nickel","Size":1,"Kind":0},{"Name":"Heat Dispersion Plate","Size":1,"Kind":0},{"Name":"Neofabric Insulation","Size":1,"Kind":2}],"Favorite":false,"Ignored":false,"Grade":2},{"Type":"Armour","Name":"Thermal Resistant Armour","Engineers":["Selene Jean"],"Ingredients":[{"Name":"Vanadium","Size":1,"Kind":0},{"Name":"Salvaged Alloys","Size":1,"Kind":0},{"Name":"Heat Exchangers","Size":1,"Kind":0},{"Name":"Bromellite","Size":1,"Kind":2}],"Favorite":false,"Ignored":false,"Grade":3},{"Type":"Torpedo Pylon","Name":"Light Weight Mount","Engineers":["Liz Ryder","Juri Ishmaak"],"Ingredients":[{"Name":"Phosphorus","Size":1,"Kind":0}],"Favorite":false,"Ignored":false,"Grade":1},{"Type":"Torpedo Pylon","Name":"Light Weight Mount","Engineers":["Liz Ryder","Juri Ishmaak"],"Ingredients":[{"Name":"Salvaged Alloys","Size":1,"Kind":0},{"Name":"Manganese","Size":1,"Kind":0},{"Name":"CMM Composite","Size":1,"Kind":2}],"Favorite":false,"Ignored":false,"Grade":2},{"Type":"Torpedo Pylon","Name":"Light Weight Mount","Engineers":["Liz Ryder","Juri Ishmaak"],"Ingredients":[{"Name":"Salvaged Alloys","Size":1,"Kind":0},{"Name":"Manganese","Size":1,"Kind":0},{"Name":"Conductive Ceramics","Size":1,"Kind":0},{"Name":"CMM Composite","Size":1,"Kind":2}],"Favorite":false,"Ignored":false,"Grade":3},{"Type":"Torpedo Pylon","Name":"Light Weight Mount","Engineers":["Liz Ryder"],"Ingredients":[{"Name":"Conductive Components","Size":1,"Kind":0},{"Name":"Proto Light Alloys","Size":1,"Kind":0},{"Name":"Magnetic Emitter Coil","Size":1,"Kind":2},{"Name":"Phase Alloys","Size":1,"Kind":0}],"Favorite":false,"Ignored":false,"Grade":4},{"Type":"Torpedo Pylon","Name":"Sturdy Mount","Engineers":["Liz Ryder","Juri Ishmaak"],"Ingredients":[{"Name":"Nickel","Size":1,"Kind":0}],"Favorite":false,"Ignored":false,"Grade":1},{"Type":"Torpedo Pylon","Name":"Sturdy Mount","Engineers":["Liz Ryder","Juri Ishmaak"],"Ingredients":[{"Name":"Nickel","Size":1,"Kind":0},{"Name":"Shield Emitters","Size":1,"Kind":0},{"Name":"HN Shock Mount","Size":1,"Kind":2}],"Favorite":false,"Ignored":false,"Grade":2},{"Type":"Torpedo Pylon","Name":"Sturdy Mount","Engineers":["Liz Ryder","Juri Ishmaak"],"Ingredients":[{"Name":"Nickel","Size":1,"Kind":0},{"Name":"Shield Emitters","Size":1,"Kind":0},{"Name":"Tungsten","Size":1,"Kind":0},{"Name":"Osmium","Size":1,"Kind":2}],"Favorite":false,"Ignored":false,"Grade":3},{"Type":"Torpedo Pylon","Name":"Sturdy Mount","Engineers":["Liz Ryder"],"Ingredients":[{"Name":"Zinc","Size":1,"Kind":0},{"Name":"Molybdenum","Size":1,"Kind":0},{"Name":"Tungsten","Size":1,"Kind":0},{"Name":"Osmium","Size":1,"Kind":2}],"Favorite":false,"Ignored":false,"Grade":4},{"Type":"Cannon","Name":"Efficient Weapon","Engineers":["Tod Quinn","The Sarge"],"Ingredients":[{"Name":"Sulphur","Size":1,"Kind":0}],"Favorite":false,"Ignored":false,"Grade":1},{"Type":"Cannon","Name":"Efficient Weapon","Engineers":["Tod Quinn","The Sarge"],"Ingredients":[{"Name":"Sulphur","Size":1,"Kind":0},{"Name":"Heat Dispersion Plate","Size":1,"Kind":0},{"Name":"Micro-Weave Cooling Hoses","Size":1,"Kind":2}],"Favorite":false,"Ignored":false,"Grade":2},{"Type":"Cannon","Name":"High Capacity Magazine","Engineers":["Tod Quinn","The Sarge"],"Ingredients":[{"Name":"Mechanical Scrap","Size":1,"Kind":0}],"Favorite":false,"Ignored":false,"Grade":1},{"Type":"Cannon","Name":"High Capacity Magazine","Engineers":["Tod Quinn","The Sarge"],"Ingredients":[{"Name":"Mechanical Scrap","Size":1,"Kind":0},{"Name":"Vanadium","Size":1,"Kind":0},{"Name":"CMM Composite","Size":1,"Kind":2}],"Favorite":false,"Ignored":false,"Grade":2},{"Type":"Cannon","Name":"Long Range Weapon","Engineers":["Tod Quinn","The Sarge"],"Ingredients":[{"Name":"Sulphur","Size":1,"Kind":0}],"Favorite":false,"Ignored":false,"Grade":1},{"Type":"Cannon","Name":"Long Range Weapon","Engineers":["Tod Quinn","The Sarge"],"Ingredients":[{"Name":"Sulphur","Size":1,"Kind":0},{"Name":"Modified Consumer Firmware","Size":1,"Kind":1},{"Name":"Insulating Membrane","Size":1,"Kind":2}],"Favorite":false,"Ignored":false,"Grade":2},{"Type":"Cannon","Name":"Short Range Blaster","Engineers":["Tod Quinn","The Sarge"],"Ingredients":[{"Name":"Nickel","Size":1,"Kind":0}],"Favorite":false,"Ignored":false,"Grade":1},{"Type":"Cannon","Name":"Short Range Blaster","Engineers":["Tod Quinn","The Sarge"],"Ingredients":[{"Name":"Nickel","Size":1,"Kind":0},{"Name":"Modified Consumer Firmware","Size":1,"Kind":1},{"Name":"Insulating Membrane","Size":1,"Kind":2}],"Favorite":false,"Ignored":false,"Grade":2},{"Type":"Cannon","Name":"Overcharged Weapon","Engineers":["Tod Quinn","The Sarge"],"Ingredients":[{"Name":"Nickel","Size":1,"Kind":0}],"Favorite":false,"Ignored":false,"Grade":1},{"Type":"Cannon","Name":"Overcharged Weapon","Engineers":["Tod Quinn","The Sarge"],"Ingredients":[{"Name":"Nickel","Size":1,"Kind":0},{"Name":"Conductive Components","Size":1,"Kind":0},{"Name":"Praseodymium","Size":1,"Kind":2}],"Favorite":false,"Ignored":false,"Grade":2},{"Type":"Frag Cannon","Name":"Double Shot","Engineers":["Tod Quinn","Zacariah Nemo"],"Ingredients":[{"Name":"Carbon","Size":1,"Kind":0}],"Favorite":false,"Ignored":false,"Grade":1},{"Type":"Frag Cannon","Name":"Double Shot","Engineers":["Tod Quinn","Zacariah Nemo"],"Ingredients":[{"Name":"Carbon","Size":1,"Kind":0},{"Name":"Mechanical Equipment","Size":1,"Kind":0},{"Name":"Micro Controllers","Size":1,"Kind":2}],"Favorite":false,"Ignored":false,"Grade":2},{"Type":"Frag Cannon","Name":"Double Shot","Engineers":["Tod Quinn","Zacariah Nemo"],"Ingredients":[{"Name":"Carbon","Size":1,"Kind":0},{"Name":"Mechanical Equipment","Size":1,"Kind":0},{"Name":"Cracked Industrial Firmware","Size":1,"Kind":1},{"Name":"Osmium","Size":1,"Kind":2}],"Favorite":false,"Ignored":false,"Grade":3},{"Type":"Frag Cannon","Name":"Double Shot","Engineers":["Zacariah Nemo"],"Ingredients":[{"Name":"Vanadium","Size":1,"Kind":0},{"Name":"Mechanical Components","Size":1,"Kind":0},{"Name":"Security Firmware Patch","Size":1,"Kind":1},{"Name":"Osmium","Size":1,"Kind":2}],"Favorite":false,"Ignored":false,"Grade":4},{"Type":"Frag Cannon","Name":"Efficient Weapon","Engineers":["Tod Quinn","Zacariah Nemo"],"Ingredients":[{"Name":"Sulphur","Size":1,"Kind":0}],"Favorite":false,"Ignored":false,"Grade":1},{"Type":"Frag Cannon","Name":"Efficient Weapon","Engineers":["Tod Quinn","Zacariah Nemo"],"Ingredients":[{"Name":"Sulphur","Size":1,"Kind":0},{"Name":"Heat Dispersion Plate","Size":1,"Kind":0},{"Name":"Micro-Weave Cooling Hoses","Size":1,"Kind":2}],"Favorite":false,"Ignored":false,"Grade":2},{"Type":"Frag Cannon","Name":"Efficient Weapon","Engineers":["Tod Quinn","Zacariah Nemo"],"Ingredients":[{"Name":"Exceptional Scrambled Emission Data","Size":1,"Kind":1},{"Name":"Chromium","Size":1,"Kind":0},{"Name":"Heat Exchangers","Size":1,"Kind":0},{"Name":"Samarium","Size":1,"Kind":2}],"Favorite":false,"Ignored":false,"Grade":3},{"Type":"Frag Cannon","Name":"Efficient Weapon","Engineers":["Zacariah Nemo"],"Ingredients":[{"Name":"Irregular Emission Data","Size":1,"Kind":1},{"Name":"Selenium","Size":1,"Kind":0},{"Name":"Heat Vanes","Size":1,"Kind":0},{"Name":"Heatsink Interlink","Size":1,"Kind":2}],"Favorite":false,"Ignored":false,"Grade":4},{"Type":"Frag Cannon","Name":"High Capacity Magazine","Engineers":["Tod Quinn","Zacariah Nemo"],"Ingredients":[{"Name":"Mechanical Scrap","Size":1,"Kind":0}],"Favorite":false,"Ignored":false,"Grade":1},{"Type":"Frag Cannon","Name":"High Capacity Magazine","Engineers":["Tod Quinn","Zacariah Nemo"],"Ingredients":[{"Name":"Mechanical Scrap","Size":1,"Kind":0},{"Name":"Vanadium","Size":1,"Kind":0},{"Name":"CMM Composite","Size":1,"Kind":2}],"Favorite":false,"Ignored":false,"Grade":2},{"Type":"Frag Cannon","Name":"High Capacity Magazine","Engineers":["Tod Quinn","Zacariah Nemo"],"Ingredients":[{"Name":"Mechanical Scrap","Size":1,"Kind":0},{"Name":"Vanadium","Size":1,"Kind":0},{"Name":"Niobium","Size":1,"Kind":0},{"Name":"Reinforced Mounting Plate","Size":1,"Kind":2}],"Favorite":false,"Ignored":false,"Grade":3},{"Type":"Frag Cannon","Name":"High Capacity Magazine","Engineers":["Zacariah Nemo"],"Ingredients":[{"Name":"Mechanical Equipment","Size":1,"Kind":0},{"Name":"High Density Composites","Size":1,"Kind":0},{"Name":"Tin","Size":1,"Kind":0},{"Name":"Reinforced Mounting Plate","Size":1,"Kind":2}],"Favorite":false,"Ignored":false,"Grade":4},{"Type":"Frag Cannon","Name":"Light Weight Mount","Engineers":["Tod Quinn","Zacariah Nemo"],"Ingredients":[{"Name":"Phosphorus","Size":1,"Kind":0}],"Favorite":false,"Ignored":false,"Grade":1},{"Type":"Frag Cannon","Name":"Light Weight Mount","Engineers":["Tod Quinn","Zacariah Nemo"],"Ingredients":[{"Name":"Salvaged Alloys","Size":1,"Kind":0},{"Name":"Manganese","Size":1,"Kind":0},{"Name":"CMM Composite","Size":1,"Kind":2}],"Favorite":false,"Ignored":false,"Grade":2},{"Type":"Frag Cannon","Name":"Light Weight Mount","Engineers":["Tod Quinn","Zacariah Nemo"],"Ingredients":[{"Name":"Salvaged Alloys","Size":1,"Kind":0},{"Name":"Manganese","Size":1,"Kind":0},{"Name":"Conductive Ceramics","Size":1,"Kind":0},{"Name":"CMM Composite","Size":1,"Kind":2}],"Favorite":false,"Ignored":false,"Grade":3},{"Type":"Frag Cannon","Name":"Light Weight Mount","Engineers":["Zacariah Nemo"],"Ingredients":[{"Name":"Conductive Components","Size":1,"Kind":0},{"Name":"Proto Light Alloys","Size":1,"Kind":0},{"Name":"Magnetic Emitter Coil","Size":1,"Kind":2},{"Name":"Phase Alloys","Size":1,"Kind":0}],"Favorite":false,"Ignored":false,"Grade":4},{"Type":"Frag Cannon","Name":"Overcharged Weapon","Engineers":["Tod Quinn","Zacariah Nemo"],"Ingredients":[{"Name":"Nickel","Size":1,"Kind":0}],"Favorite":false,"Ignored":false,"Grade":1},{"Type":"Frag Cannon","Name":"Overcharged Weapon","Engineers":["Tod Quinn","Zacariah Nemo"],"Ingredients":[{"Name":"Nickel","Size":1,"Kind":0},{"Name":"Conductive Components","Size":1,"Kind":0},{"Name":"Praseodymium","Size":1,"Kind":2}],"Favorite":false,"Ignored":false,"Grade":2},{"Type":"Frag Cannon","Name":"Overcharged Weapon","Engineers":["Tod Quinn","Zacariah Nemo"],"Ingredients":[{"Name":"Nickel","Size":1,"Kind":0},{"Name":"Conductive Components","Size":1,"Kind":0},{"Name":"Electrochemical Arrays","Size":1,"Kind":0},{"Name":"Articulation Motors","Size":1,"Kind":2}],"Favorite":false,"Ignored":false,"Grade":3},{"Type":"Frag Cannon","Name":"Overcharged Weapon","Engineers":["Zacariah Nemo"],"Ingredients":[{"Name":"Zinc","Size":1,"Kind":0},{"Name":"Conductive Ceramics","Size":1,"Kind":0},{"Name":"Polymer Capacitors","Size":1,"Kind":0},{"Name":"Articulation Motors","Size":1,"Kind":2}],"Favorite":false,"Ignored":false,"Grade":4},{"Type":"Frag Cannon","Name":"Sturdy Mount","Engineers":["Tod Quinn","Zacariah Nemo"],"Ingredients":[{"Name":"Nickel","Size":1,"Kind":0}],"Favorite":false,"Ignored":false,"Grade":1},{"Type":"Frag Cannon","Name":"Sturdy Mount","Engineers":["Tod Quinn","Zacariah Nemo"],"Ingredients":[{"Name":"Nickel","Size":1,"Kind":0},{"Name":"Shield Emitters","Size":1,"Kind":0},{"Name":"HN Shock Mount","Size":1,"Kind":2}],"Favorite":false,"Ignored":false,"Grade":2},{"Type":"Frag Cannon","Name":"Sturdy Mount","Engineers":["Tod Quinn","Zacariah Nemo"],"Ingredients":[{"Name":"Nickel","Size":1,"Kind":0},{"Name":"Shield Emitters","Size":1,"Kind":0},{"Name":"Tungsten","Size":1,"Kind":0},{"Name":"Osmium","Size":1,"Kind":2}],"Favorite":false,"Ignored":false,"Grade":3},{"Type":"Frag Cannon","Name":"Sturdy Mount","Engineers":["Zacariah Nemo"],"Ingredients":[{"Name":"Zinc","Size":1,"Kind":0},{"Name":"Molybdenum","Size":1,"Kind":0},{"Name":"Tungsten","Size":1,"Kind":0},{"Name":"Osmium","Size":1,"Kind":2}],"Favorite":false,"Ignored":false,"Grade":4},{"Type":"Multi-Cannon","Name":"Efficient Weapon","Engineers":["Tod Quinn","Zacariah Nemo"],"Ingredients":[{"Name":"Sulphur","Size":1,"Kind":0}],"Favorite":false,"Ignored":false,"Grade":1},{"Type":"Multi-Cannon","Name":"Efficient Weapon","Engineers":["Tod Quinn","Zacariah Nemo"],"Ingredients":[{"Name":"Sulphur","Size":1,"Kind":0},{"Name":"Heat Dispersion Plate","Size":1,"Kind":0},{"Name":"Micro-Weave Cooling Hoses","Size":1,"Kind":2}],"Favorite":false,"Ignored":false,"Grade":2},{"Type":"Multi-Cannon","Name":"Efficient Weapon","Engineers":["Tod Quinn","Zacariah Nemo"],"Ingredients":[{"Name":"Exceptional Scrambled Emission Data","Size":1,"Kind":1},{"Name":"Chromium","Size":1,"Kind":0},{"Name":"Heat Exchangers","Size":1,"Kind":0},{"Name":"Samarium","Size":1,"Kind":2}],"Favorite":false,"Ignored":false,"Grade":3},{"Type":"Multi-Cannon","Name":"Efficient Weapon","Engineers":["Tod Quinn"],"Ingredients":[{"Name":"Irregular Emission Data","Size":1,"Kind":1},{"Name":"Selenium","Size":1,"Kind":0},{"Name":"Heat Vanes","Size":1,"Kind":0},{"Name":"Heatsink Interlink","Size":1,"Kind":2}],"Favorite":false,"Ignored":false,"Grade":4},{"Type":"Multi-Cannon","Name":"Efficient Weapon","Engineers":["Tod Quinn"],"Ingredients":[{"Name":"Unexpected Emission Data","Size":1,"Kind":1},{"Name":"Cadmium","Size":1,"Kind":0},{"Name":"Proto Heat Radiators","Size":1,"Kind":0},{"Name":"Heatsink Interlink","Size":1,"Kind":2}],"Favorite":false,"Ignored":false,"Grade":5},{"Type":"Multi-Cannon","Name":"High Capacity Magazine","Engineers":["Tod Quinn","Zacariah Nemo"],"Ingredients":[{"Name":"Mechanical Scrap","Size":1,"Kind":0}],"Favorite":false,"Ignored":false,"Grade":1},{"Type":"Multi-Cannon","Name":"High Capacity Magazine","Engineers":["Tod Quinn","Zacariah Nemo"],"Ingredients":[{"Name":"Mechanical Scrap","Size":1,"Kind":0},{"Name":"Vanadium","Size":1,"Kind":0},{"Name":"CMM Composite","Size":1,"Kind":2}],"Favorite":false,"Ignored":false,"Grade":2},{"Type":"Multi-Cannon","Name":"High Capacity Magazine","Engineers":["Tod Quinn","Zacariah Nemo"],"Ingredients":[{"Name":"Mechanical Scrap","Size":1,"Kind":0},{"Name":"Vanadium","Size":1,"Kind":0},{"Name":"Niobium","Size":1,"Kind":0},{"Name":"Reinforced Mounting Plate","Size":1,"Kind":2}],"Favorite":false,"Ignored":false,"Grade":3},{"Type":"Multi-Cannon","Name":"High Capacity Magazine","Engineers":["Tod Quinn"],"Ingredients":[{"Name":"Mechanical Equipment","Size":1,"Kind":0},{"Name":"High Density Composites","Size":1,"Kind":0},{"Name":"Tin","Size":1,"Kind":0},{"Name":"Reinforced Mounting Plate","Size":1,"Kind":2}],"Favorite":false,"Ignored":false,"Grade":4},{"Type":"Multi-Cannon","Name":"High Capacity Magazine","Engineers":["Tod Quinn"],"Ingredients":[{"Name":"Mechanical Components","Size":1,"Kind":0},{"Name":"Proprietary Composites","Size":1,"Kind":0},{"Name":"Military Supercapacitors","Size":1,"Kind":0},{"Name":"Reinforced Mounting Plate","Size":1,"Kind":2}],"Favorite":false,"Ignored":false,"Grade":5},{"Type":"Multi-Cannon","Name":"Light Weight Mount","Engineers":["Tod Quinn","Zacariah Nemo"],"Ingredients":[{"Name":"Phosphorus","Size":1,"Kind":0}],"Favorite":false,"Ignored":false,"Grade":1},{"Type":"Multi-Cannon","Name":"Light Weight Mount","Engineers":["Tod Quinn","Zacariah Nemo"],"Ingredients":[{"Name":"Salvaged Alloys","Size":1,"Kind":0},{"Name":"Manganese","Size":1,"Kind":0},{"Name":"CMM Composite","Size":1,"Kind":2}],"Favorite":false,"Ignored":false,"Grade":2},{"Type":"Multi-Cannon","Name":"Light Weight Mount","Engineers":["Tod Quinn","Zacariah Nemo"],"Ingredients":[{"Name":"Salvaged Alloys","Size":1,"Kind":0},{"Name":"Manganese","Size":1,"Kind":0},{"Name":"Conductive Ceramics","Size":1,"Kind":0},{"Name":"CMM Composite","Size":1,"Kind":2}],"Favorite":false,"Ignored":false,"Grade":3},{"Type":"Multi-Cannon","Name":"Light Weight Mount","Engineers":["Tod Quinn"],"Ingredients":[{"Name":"Conductive Components","Size":1,"Kind":0},{"Name":"Proto Light Alloys","Size":1,"Kind":0},{"Name":"Magnetic Emitter Coil","Size":1,"Kind":2},{"Name":"Phase Alloys","Size":1,"Kind":0}],"Favorite":false,"Ignored":false,"Grade":4},{"Type":"Multi-Cannon","Name":"Light Weight Mount","Engineers":["Tod Quinn"],"Ingredients":[{"Name":"Conductive Ceramics","Size":1,"Kind":0},{"Name":"Proto Light Alloys","Size":1,"Kind":0},{"Name":"Magnetic Emitter Coil","Size":1,"Kind":2},{"Name":"Proto Radiolic Alloys","Size":1,"Kind":0}],"Favorite":false,"Ignored":false,"Grade":5},{"Type":"Multi-Cannon","Name":"Overcharged Weapon","Engineers":["Tod Quinn","Zacariah Nemo"],"Ingredients":[{"Name":"Nickel","Size":1,"Kind":0}],"Favorite":false,"Ignored":false,"Grade":1},{"Type":"Multi-Cannon","Name":"Overcharged Weapon","Engineers":["Tod Quinn","Zacariah Nemo"],"Ingredients":[{"Name":"Nickel","Size":1,"Kind":0},{"Name":"Conductive Components","Size":1,"Kind":0},{"Name":"Praseodymium","Size":1,"Kind":2}],"Favorite":false,"Ignored":false,"Grade":2},{"Type":"Multi-Cannon","Name":"Overcharged Weapon","Engineers":["Tod Quinn","Zacariah Nemo"],"Ingredients":[{"Name":"Nickel","Size":1,"Kind":0},{"Name":"Conductive Components","Size":1,"Kind":0},{"Name":"Electrochemical Arrays","Size":1,"Kind":0},{"Name":"Articulation Motors","Size":1,"Kind":2}],"Favorite":false,"Ignored":false,"Grade":3},{"Type":"Multi-Cannon","Name":"Overcharged Weapon","Engineers":["Tod Quinn"],"Ingredients":[{"Name":"Zinc","Size":1,"Kind":0},{"Name":"Conductive Ceramics","Size":1,"Kind":0},{"Name":"Polymer Capacitors","Size":1,"Kind":0},{"Name":"Articulation Motors","Size":1,"Kind":2}],"Favorite":false,"Ignored":false,"Grade":4},{"Type":"Multi-Cannon","Name":"Overcharged Weapon","Engineers":["Tod Quinn"],"Ingredients":[{"Name":"Zirconium","Size":1,"Kind":0},{"Name":"Conductive Polymers","Size":1,"Kind":0},{"Name":"Modified Embedded Firmware","Size":1,"Kind":1},{"Name":"Reinforced Mounting Plate","Size":1,"Kind":2}],"Favorite":false,"Ignored":false,"Grade":5},{"Type":"Multi-Cannon","Name":"Short Range Blaster","Engineers":["Tod Quinn","Zacariah Nemo"],"Ingredients":[{"Name":"Nickel","Size":1,"Kind":0}],"Favorite":false,"Ignored":false,"Grade":1},{"Type":"Multi-Cannon","Name":"Short Range Blaster","Engineers":["Tod Quinn","Zacariah Nemo"],"Ingredients":[{"Name":"Nickel","Size":1,"Kind":0},{"Name":"Modified Consumer Firmware","Size":1,"Kind":1},{"Name":"Insulating Membrane","Size":1,"Kind":2}],"Favorite":false,"Ignored":false,"Grade":2},{"Type":"Multi-Cannon","Name":"Short Range Blaster","Engineers":["Tod Quinn","Zacariah Nemo"],"Ingredients":[{"Name":"Nickel","Size":1,"Kind":0},{"Name":"Modified Consumer Firmware","Size":1,"Kind":1},{"Name":"Electrochemical Arrays","Size":1,"Kind":0},{"Name":"Neofabric Insulation","Size":1,"Kind":2}],"Favorite":false,"Ignored":false,"Grade":3},{"Type":"Multi-Cannon","Name":"Short Range Blaster","Engineers":["Tod Quinn"],"Ingredients":[{"Name":"Modified Consumer Firmware","Size":1,"Kind":1},{"Name":"Electrochemical Arrays","Size":1,"Kind":0},{"Name":"Conductive Polymers","Size":1,"Kind":0},{"Name":"Platinum","Size":1,"Kind":2}],"Favorite":false,"Ignored":false,"Grade":4},{"Type":"Multi-Cannon","Name":"Short Range Blaster","Engineers":["Tod Quinn"],"Ingredients":[{"Name":"Biotech Conductors","Size":1,"Kind":0},{"Name":"Configurable Components","Size":1,"Kind":0},{"Name":"Cracked Industrial Firmware","Size":1,"Kind":1},{"Name":"Magnetic Emitter Coil","Size":1,"Kind":2}],"Favorite":false,"Ignored":false,"Grade":5},{"Type":"Multi-Cannon","Name":"Sturdy Mount","Engineers":["Tod Quinn","Zacariah Nemo"],"Ingredients":[{"Name":"Nickel","Size":1,"Kind":0}],"Favorite":false,"Ignored":false,"Grade":1},{"Type":"Multi-Cannon","Name":"Sturdy Mount","Engineers":["Tod Quinn","Zacariah Nemo"],"Ingredients":[{"Name":"Nickel","Size":1,"Kind":0},{"Name":"Shield Emitters","Size":1,"Kind":0},{"Name":"HN Shock Mount","Size":1,"Kind":2}],"Favorite":false,"Ignored":false,"Grade":2},{"Type":"Multi-Cannon","Name":"Sturdy Mount","Engineers":["Tod Quinn","Zacariah Nemo"],"Ingredients":[{"Name":"Nickel","Size":1,"Kind":0},{"Name":"Shield Emitters","Size":1,"Kind":0},{"Name":"Tungsten","Size":1,"Kind":0},{"Name":"Osmium","Size":1,"Kind":2}],"Favorite":false,"Ignored":false,"Grade":3},{"Type":"Multi-Cannon","Name":"Sturdy Mount","Engineers":["Tod Quinn"],"Ingredients":[{"Name":"Zinc","Size":1,"Kind":0},{"Name":"Molybdenum","Size":1,"Kind":0},{"Name":"Tungsten","Size":1,"Kind":0},{"Name":"Osmium","Size":1,"Kind":2}],"Favorite":false,"Ignored":false,"Grade":4},{"Type":"Multi-Cannon","Name":"Sturdy Mount","Engineers":["Tod Quinn"],"Ingredients":[{"Name":"High Density Composites","Size":1,"Kind":0},{"Name":"Molybdenum","Size":1,"Kind":0},{"Name":"Technetium","Size":1,"Kind":0},{"Name":"Radiation Baffle","Size":1,"Kind":2}],"Favorite":false,"Ignored":false,"Grade":5},{"Type":"Rail Gun","Name":"High Capacity Magazine","Engineers":["Tod Quinn","The Sarge"],"Ingredients":[{"Name":"Mechanical Scrap","Size":1,"Kind":0}],"Favorite":false,"Ignored":false,"Grade":1},{"Type":"Rail Gun","Name":"High Capacity Magazine","Engineers":["Tod Quinn","The Sarge"],"Ingredients":[{"Name":"Mechanical Scrap","Size":1,"Kind":0},{"Name":"Vanadium","Size":1,"Kind":0},{"Name":"CMM Composite","Size":1,"Kind":2}],"Favorite":false,"Ignored":false,"Grade":2},{"Type":"Rail Gun","Name":"Light Weight Mount","Engineers":["Tod Quinn","The Sarge"],"Ingredients":[{"Name":"Phosphorus","Size":1,"Kind":0}],"Favorite":false,"Ignored":false,"Grade":1},{"Type":"Rail Gun","Name":"Light Weight Mount","Engineers":["Tod Quinn","The Sarge"],"Ingredients":[{"Name":"Salvaged Alloys","Size":1,"Kind":0},{"Name":"Manganese","Size":1,"Kind":0},{"Name":"CMM Composite","Size":1,"Kind":2}],"Favorite":false,"Ignored":false,"Grade":2},{"Type":"Rail Gun","Name":"Long Range Weapon","Engineers":["Tod Quinn","The Sarge"],"Ingredients":[{"Name":"Sulphur","Size":1,"Kind":0}],"Favorite":false,"Ignored":false,"Grade":1},{"Type":"Rail Gun","Name":"Long Range Weapon","Engineers":["Tod Quinn","The Sarge"],"Ingredients":[{"Name":"Sulphur","Size":1,"Kind":0},{"Name":"Modified Consumer Firmware","Size":1,"Kind":1},{"Name":"Insulating Membrane","Size":1,"Kind":2}],"Favorite":false,"Ignored":false,"Grade":2},{"Type":"Rail Gun","Name":"Short Range Blaster","Engineers":["Tod Quinn","The Sarge"],"Ingredients":[{"Name":"Nickel","Size":1,"Kind":0}],"Favorite":false,"Ignored":false,"Grade":1},{"Type":"Rail Gun","Name":"Short Range Blaster","Engineers":["Tod Quinn","The Sarge"],"Ingredients":[{"Name":"Nickel","Size":1,"Kind":0},{"Name":"Modified Consumer Firmware","Size":1,"Kind":1},{"Name":"Insulating Membrane","Size":1,"Kind":2}],"Favorite":false,"Ignored":false,"Grade":2},{"Type":"Rail Gun","Name":"Sturdy Mount","Engineers":["Tod Quinn","The Sarge"],"Ingredients":[{"Name":"Nickel","Size":1,"Kind":0}],"Favorite":false,"Ignored":false,"Grade":1},{"Type":"Rail Gun","Name":"Sturdy Mount","Engineers":["Tod Quinn","The Sarge"],"Ingredients":[{"Name":"Nickel","Size":1,"Kind":0},{"Name":"Shield Emitters","Size":1,"Kind":0},{"Name":"HN Shock Mount","Size":1,"Kind":2}],"Favorite":false,"Ignored":false,"Grade":2},{"Type":"Distributor","Name":"High Charge Capacity Power Distributor","Engineers":["The Dweller","Marco Qwent","Hera Tani"],"Ingredients":[{"Name":"Sulphur","Size":1,"Kind":0}],"Favorite":false,"Ignored":false,"Grade":1},{"Type":"Distributor","Name":"High Charge Capacity Power Distributor","Engineers":["The Dweller","Marco Qwent","Hera Tani"],"Ingredients":[{"Name":"Specialised Legacy Firmware","Size":1,"Kind":1},{"Name":"Chromium","Size":1,"Kind":0},{"Name":"Platinum","Size":1,"Kind":2}],"Favorite":false,"Ignored":false,"Grade":2},{"Type":"Distributor","Name":"High Charge Capacity Power Distributor","Engineers":["The Dweller","Marco Qwent","Hera Tani"],"Ingredients":[{"Name":"Specialised Legacy Firmware","Size":1,"Kind":1},{"Name":"Chromium","Size":1,"Kind":0},{"Name":"High Density Composites","Size":1,"Kind":0},{"Name":"Modular Terminals","Size":1,"Kind":2}],"Favorite":false,"Ignored":false,"Grade":3},{"Type":"Distributor","Name":"High Charge Capacity Power Distributor","Engineers":["The Dweller"],"Ingredients":[{"Name":"Modified Consumer Firmware","Size":1,"Kind":1},{"Name":"Selenium","Size":1,"Kind":0},{"Name":"Proprietary Composites","Size":1,"Kind":0},{"Name":"Modular Terminals","Size":1,"Kind":2}],"Favorite":false,"Ignored":false,"Grade":4},{"Type":"Distributor","Name":"High Charge Capacity Power Distributor","Engineers":["The Dweller"],"Ingredients":[{"Name":"Cracked Industrial Firmware","Size":1,"Kind":1},{"Name":"Proprietary Composites","Size":1,"Kind":0},{"Name":"Military Supercapacitors","Size":1,"Kind":0},{"Name":"Emergency Power Cells","Size":1,"Kind":2}],"Favorite":false,"Ignored":false,"Grade":5},{"Type":"Distributor","Name":"Charge Enhanced Power Distributor","Engineers":["The Dweller","Marco Qwent","Hera Tani"],"Ingredients":[{"Name":"Specialised Legacy Firmware","Size":1,"Kind":1}],"Favorite":false,"Ignored":false,"Grade":1},{"Type":"Distributor","Name":"Charge Enhanced Power Distributor","Engineers":["The Dweller","Marco Qwent","Hera Tani"],"Ingredients":[{"Name":"Specialised Legacy Firmware","Size":1,"Kind":1},{"Name":"Chemical Processors","Size":1,"Kind":0},{"Name":"Nanobreakers","Size":1,"Kind":2}],"Favorite":false,"Ignored":false,"Grade":2},{"Type":"Distributor","Name":"Charge Enhanced Power Distributor","Engineers":["The Dweller","Marco Qwent","Hera Tani"],"Ingredients":[{"Name":"Grid Resistors","Size":1,"Kind":0},{"Name":"Modified Consumer Firmware","Size":1,"Kind":1},{"Name":"Chemical Distillery","Size":1,"Kind":0},{"Name":"Praseodymium","Size":1,"Kind":2}],"Favorite":false,"Ignored":false,"Grade":3},{"Type":"Distributor","Name":"Charge Enhanced Power Distributor","Engineers":["The Dweller"],"Ingredients":[{"Name":"Hybrid Capacitors","Size":1,"Kind":0},{"Name":"Cracked Industrial Firmware","Size":1,"Kind":1},{"Name":"Chemical Manipulators","Size":1,"Kind":0},{"Name":"Ion Distributor","Size":1,"Kind":2}],"Favorite":false,"Ignored":false,"Grade":4},{"Type":"Distributor","Name":"Charge Enhanced Power Distributor","Engineers":["The Dweller"],"Ingredients":[{"Name":"Cracked Industrial Firmware","Size":1,"Kind":1},{"Name":"Chemical Manipulators","Size":1,"Kind":0},{"Name":"Exquisite Focus Crystals","Size":1,"Kind":0},{"Name":"Ion Distributor","Size":1,"Kind":2}],"Favorite":false,"Ignored":false,"Grade":5},{"Type":"Distributor","Name":"Engine Focused Power Distributor","Engineers":["The Dweller","Marco Qwent","Hera Tani"],"Ingredients":[{"Name":"Sulphur","Size":1,"Kind":0}],"Favorite":false,"Ignored":false,"Grade":1},{"Type":"Distributor","Name":"Engine Focused Power Distributor","Engineers":["The Dweller","Marco Qwent","Hera Tani"],"Ingredients":[{"Name":"Sulphur","Size":1,"Kind":0},{"Name":"Conductive Components","Size":1,"Kind":0},{"Name":"Nanobreakers","Size":1,"Kind":2}],"Favorite":false,"Ignored":false,"Grade":2},{"Type":"Distributor","Name":"Engine Focused Power Distributor","Engineers":["The Dweller","Marco Qwent","Hera Tani"],"Ingredients":[{"Name":"Anomalous Bulk Scan Data","Size":1,"Kind":1},{"Name":"Chromium","Size":1,"Kind":0},{"Name":"Electrochemical Arrays","Size":1,"Kind":0},{"Name":"Nanobreakers","Size":1,"Kind":2}],"Favorite":false,"Ignored":false,"Grade":3},{"Type":"Distributor","Name":"System Focused Power Distributor","Engineers":["The Dweller","Marco Qwent","Hera Tani"],"Ingredients":[{"Name":"Sulphur","Size":1,"Kind":0}],"Favorite":false,"Ignored":false,"Grade":1},{"Type":"Distributor","Name":"System Focused Power Distributor","Engineers":["The Dweller","Marco Qwent","Hera Tani"],"Ingredients":[{"Name":"Sulphur","Size":1,"Kind":0},{"Name":"Conductive Components","Size":1,"Kind":0},{"Name":"Nanobreakers","Size":1,"Kind":2}],"Favorite":false,"Ignored":false,"Grade":2},{"Type":"Distributor","Name":"System Focused Power Distributor","Engineers":["The Dweller","Marco Qwent","Hera Tani"],"Ingredients":[{"Name":"Anomalous Bulk Scan Data","Size":1,"Kind":1},{"Name":"Chromium","Size":1,"Kind":0},{"Name":"Electrochemical Arrays","Size":1,"Kind":0},{"Name":"Nanobreakers","Size":1,"Kind":2}],"Favorite":false,"Ignored":false,"Grade":3},{"Type":"Distributor","Name":"Weapon Focused Power Distributor","Engineers":["The Dweller","Marco Qwent","Hera Tani"],"Ingredients":[{"Name":"Sulphur","Size":1,"Kind":0}],"Favorite":false,"Ignored":false,"Grade":1},{"Type":"Distributor","Name":"Weapon Focused Power Distributor","Engineers":["The Dweller","Marco Qwent","Hera Tani"],"Ingredients":[{"Name":"Sulphur","Size":1,"Kind":0},{"Name":"Conductive Components","Size":1,"Kind":0},{"Name":"Nanobreakers","Size":1,"Kind":2}],"Favorite":false,"Ignored":false,"Grade":2},{"Type":"Distributor","Name":"Weapon Focused Power Distributor","Engineers":["The Dweller","Marco Qwent","Hera Tani"],"Ingredients":[{"Name":"Anomalous Bulk Scan Data","Size":1,"Kind":1},{"Name":"Selenium","Size":1,"Kind":0},{"Name":"Hybrid Capacitors","Size":1,"Kind":0},{"Name":"Nanobreakers","Size":1,"Kind":2}],"Favorite":false,"Ignored":false,"Grade":3},{"Type":"Distributor","Name":"Shielded Power Distributor","Engineers":["The Dweller","Marco Qwent","Hera Tani"],"Ingredients":[{"Name":"Worn Shield Emitters","Size":1,"Kind":0}],"Favorite":false,"Ignored":false,"Grade":1},{"Type":"Distributor","Name":"Shielded Power Distributor","Engineers":["The Dweller","Marco Qwent","Hera Tani"],"Ingredients":[{"Name":"Carbon","Size":1,"Kind":0},{"Name":"Shield Emitters","Size":1,"Kind":0},{"Name":"CMM Composite","Size":1,"Kind":2}],"Favorite":false,"Ignored":false,"Grade":2},{"Type":"Distributor","Name":"Shielded Power Distributor","Engineers":["The Dweller","Marco Qwent","Hera Tani"],"Ingredients":[{"Name":"Carbon","Size":1,"Kind":0},{"Name":"Shield Emitters","Size":1,"Kind":0},{"Name":"High Density Composites","Size":1,"Kind":0},{"Name":"Osmium","Size":1,"Kind":2}],"Favorite":false,"Ignored":false,"Grade":3},{"Type":"Distributor","Name":"Shielded Power Distributor","Engineers":["The Dweller"],"Ingredients":[{"Name":"Vanadium","Size":1,"Kind":0},{"Name":"Shielding Sensors","Size":1,"Kind":0},{"Name":"Proprietary Composites","Size":1,"Kind":0},{"Name":"Reinforced Mounting Plate","Size":1,"Kind":2}],"Favorite":false,"Ignored":false,"Grade":4},{"Type":"Distributor","Name":"Shielded Power Distributor","Engineers":["The Dweller"],"Ingredients":[{"Name":"Tungsten","Size":1,"Kind":0},{"Name":"Compound Shielding","Size":1,"Kind":0},{"Name":"Core Dynamics Composites","Size":1,"Kind":0},{"Name":"Reinforced Mounting Plate","Size":1,"Kind":2}],"Favorite":false,"Ignored":false,"Grade":5},{"Type":"Pulse Laser","Name":"Efficient Weapon","Engineers":["The Dweller","Broo Tarquin"],"Ingredients":[{"Name":"Sulphur","Size":1,"Kind":0}],"Favorite":false,"Ignored":false,"Grade":1},{"Type":"Pulse Laser","Name":"Efficient Weapon","Engineers":["The Dweller","Broo Tarquin"],"Ingredients":[{"Name":"Sulphur","Size":1,"Kind":0},{"Name":"Heat Dispersion Plate","Size":1,"Kind":0},{"Name":"Micro-Weave Cooling Hoses","Size":1,"Kind":2}],"Favorite":false,"Ignored":false,"Grade":2},{"Type":"Pulse Laser","Name":"Efficient Weapon","Engineers":["The Dweller","Broo Tarquin"],"Ingredients":[{"Name":"Exceptional Scrambled Emission Data","Size":1,"Kind":1},{"Name":"Chromium","Size":1,"Kind":0},{"Name":"Heat Exchangers","Size":1,"Kind":0},{"Name":"Samarium","Size":1,"Kind":2}],"Favorite":false,"Ignored":false,"Grade":3},{"Type":"Pulse Laser","Name":"Efficient Weapon","Engineers":["Broo Tarquin"],"Ingredients":[{"Name":"Irregular Emission Data","Size":1,"Kind":1},{"Name":"Selenium","Size":1,"Kind":0},{"Name":"Heat Vanes","Size":1,"Kind":0},{"Name":"Heatsink Interlink","Size":1,"Kind":2}],"Favorite":false,"Ignored":false,"Grade":4},{"Type":"Pulse Laser","Name":"Focused Weapon","Engineers":["The Dweller","Broo Tarquin"],"Ingredients":[{"Name":"Iron","Size":1,"Kind":0}],"Favorite":false,"Ignored":false,"Grade":1},{"Type":"Pulse Laser","Name":"Focused Weapon","Engineers":["The Dweller","Broo Tarquin"],"Ingredients":[{"Name":"Iron","Size":1,"Kind":0},{"Name":"Conductive Components","Size":1,"Kind":0},{"Name":"Micro Controllers","Size":1,"Kind":2}],"Favorite":false,"Ignored":false,"Grade":2},{"Type":"Pulse Laser","Name":"Focused Weapon","Engineers":["The Dweller","Broo Tarquin"],"Ingredients":[{"Name":"Iron","Size":1,"Kind":0},{"Name":"Chromium","Size":1,"Kind":0},{"Name":"Conductive Ceramics","Size":1,"Kind":0},{"Name":"Platinum","Size":1,"Kind":2}],"Favorite":false,"Ignored":false,"Grade":3},{"Type":"Pulse Laser","Name":"Focused Weapon","Engineers":["Broo Tarquin"],"Ingredients":[{"Name":"Germanium","Size":1,"Kind":0},{"Name":"Focus Crystals","Size":1,"Kind":0},{"Name":"Polymer Capacitors","Size":1,"Kind":0},{"Name":"Nanobreakers","Size":1,"Kind":2}],"Favorite":false,"Ignored":false,"Grade":4},{"Type":"Pulse Laser","Name":"Light Weight Mount","Engineers":["The Dweller","Broo Tarquin"],"Ingredients":[{"Name":"Phosphorus","Size":1,"Kind":0}],"Favorite":false,"Ignored":false,"Grade":1},{"Type":"Pulse Laser","Name":"Light Weight Mount","Engineers":["The Dweller","Broo Tarquin"],"Ingredients":[{"Name":"Salvaged Alloys","Size":1,"Kind":0},{"Name":"Manganese","Size":1,"Kind":0},{"Name":"CMM Composite","Size":1,"Kind":2}],"Favorite":false,"Ignored":false,"Grade":2},{"Type":"Pulse Laser","Name":"Light Weight Mount","Engineers":["The Dweller","Broo Tarquin"],"Ingredients":[{"Name":"Salvaged Alloys","Size":1,"Kind":0},{"Name":"Manganese","Size":1,"Kind":0},{"Name":"Conductive Ceramics","Size":1,"Kind":0},{"Name":"CMM Composite","Size":1,"Kind":2}],"Favorite":false,"Ignored":false,"Grade":3},{"Type":"Pulse Laser","Name":"Light Weight Mount","Engineers":["Broo Tarquin"],"Ingredients":[{"Name":"Conductive Components","Size":1,"Kind":0},{"Name":"Proto Light Alloys","Size":1,"Kind":0},{"Name":"Magnetic Emitter Coil","Size":1,"Kind":2},{"Name":"Phase Alloys","Size":1,"Kind":0}],"Favorite":false,"Ignored":false,"Grade":4},{"Type":"Pulse Laser","Name":"Sturdy Mount","Engineers":["The Dweller","Broo Tarquin"],"Ingredients":[{"Name":"Nickel","Size":1,"Kind":0}],"Favorite":false,"Ignored":false,"Grade":1},{"Type":"Pulse Laser","Name":"Sturdy Mount","Engineers":["The Dweller","Broo Tarquin"],"Ingredients":[{"Name":"Nickel","Size":1,"Kind":0},{"Name":"Shield Emitters","Size":1,"Kind":0},{"Name":"HN Shock Mount","Size":1,"Kind":2}],"Favorite":false,"Ignored":false,"Grade":2},{"Type":"Pulse Laser","Name":"Sturdy Mount","Engineers":["The Dweller","Broo Tarquin"],"Ingredients":[{"Name":"Nickel","Size":1,"Kind":0},{"Name":"Shield Emitters","Size":1,"Kind":0},{"Name":"Tungsten","Size":1,"Kind":0},{"Name":"Osmium","Size":1,"Kind":2}],"Favorite":false,"Ignored":false,"Grade":3},{"Type":"Pulse Laser","Name":"Sturdy Mount","Engineers":["Broo Tarquin"],"Ingredients":[{"Name":"Zinc","Size":1,"Kind":0},{"Name":"Molybdenum","Size":1,"Kind":0},{"Name":"Tungsten","Size":1,"Kind":0},{"Name":"Osmium","Size":1,"Kind":2}],"Favorite":false,"Ignored":false,"Grade":4},{"Type":"Pulse Laser","Name":"Overcharged Weapon","Engineers":["The Dweller","Broo Tarquin"],"Ingredients":[{"Name":"Nickel","Size":1,"Kind":0}],"Favorite":false,"Ignored":false,"Grade":1},{"Type":"Pulse Laser","Name":"Overcharged Weapon","Engineers":["The Dweller","Broo Tarquin"],"Ingredients":[{"Name":"Nickel","Size":1,"Kind":0},{"Name":"Conductive Components","Size":1,"Kind":0},{"Name":"Praseodymium","Size":1,"Kind":2}],"Favorite":false,"Ignored":false,"Grade":2},{"Type":"Pulse Laser","Name":"Overcharged Weapon","Engineers":["The Dweller","Broo Tarquin"],"Ingredients":[{"Name":"Nickel","Size":1,"Kind":0},{"Name":"Conductive Components","Size":1,"Kind":0},{"Name":"Electrochemical Arrays","Size":1,"Kind":0},{"Name":"Articulation Motors","Size":1,"Kind":2}],"Favorite":false,"Ignored":false,"Grade":3},{"Type":"Pulse Laser","Name":"Overcharged Weapon","Engineers":["Broo Tarquin"],"Ingredients":[{"Name":"Zinc","Size":1,"Kind":0},{"Name":"Conductive Ceramics","Size":1,"Kind":0},{"Name":"Polymer Capacitors","Size":1,"Kind":0},{"Name":"Articulation Motors","Size":1,"Kind":2}],"Favorite":false,"Ignored":false,"Grade":4},{"Type":"Burst Laser","Name":"Efficient Weapon","Engineers":["The Dweller","Broo Tarquin"],"Ingredients":[{"Name":"Sulphur","Size":1,"Kind":0}],"Favorite":false,"Ignored":false,"Grade":1},{"Type":"Burst Laser","Name":"Efficient Weapon","Engineers":["The Dweller","Broo Tarquin"],"Ingredients":[{"Name":"Sulphur","Size":1,"Kind":0},{"Name":"Heat Dispersion Plate","Size":1,"Kind":0},{"Name":"Micro-Weave Cooling Hoses","Size":1,"Kind":2}],"Favorite":false,"Ignored":false,"Grade":2},{"Type":"Burst Laser","Name":"Efficient Weapon","Engineers":["Broo Tarquin"],"Ingredients":[{"Name":"Exceptional Scrambled Emission Data","Size":1,"Kind":1},{"Name":"Chromium","Size":1,"Kind":0},{"Name":"Heat Exchangers","Size":1,"Kind":0},{"Name":"Samarium","Size":1,"Kind":2}],"Favorite":false,"Ignored":false,"Grade":3},{"Type":"Burst Laser","Name":"Light Weight Mount","Engineers":["The Dweller","Broo Tarquin"],"Ingredients":[{"Name":"Phosphorus","Size":1,"Kind":0}],"Favorite":false,"Ignored":false,"Grade":1},{"Type":"Burst Laser","Name":"Light Weight Mount","Engineers":["The Dweller","Broo Tarquin"],"Ingredients":[{"Name":"Salvaged Alloys","Size":1,"Kind":0},{"Name":"Manganese","Size":1,"Kind":0},{"Name":"CMM Composite","Size":1,"Kind":2}],"Favorite":false,"Ignored":false,"Grade":2},{"Type":"Burst Laser","Name":"Light Weight Mount","Engineers":["Broo Tarquin"],"Ingredients":[{"Name":"Salvaged Alloys","Size":1,"Kind":0},{"Name":"Manganese","Size":1,"Kind":0},{"Name":"Conductive Ceramics","Size":1,"Kind":0},{"Name":"CMM Composite","Size":1,"Kind":2}],"Favorite":false,"Ignored":false,"Grade":3},{"Type":"Burst Laser","Name":"Sturdy Mount","Engineers":["The Dweller","Broo Tarquin"],"Ingredients":[{"Name":"Nickel","Size":1,"Kind":0}],"Favorite":false,"Ignored":false,"Grade":1},{"Type":"Burst Laser","Name":"Sturdy Mount","Engineers":["The Dweller","Broo Tarquin"],"Ingredients":[{"Name":"Nickel","Size":1,"Kind":0},{"Name":"Shield Emitters","Size":1,"Kind":0},{"Name":"HN Shock Mount","Size":1,"Kind":2}],"Favorite":false,"Ignored":false,"Grade":2},{"Type":"Burst Laser","Name":"Sturdy Mount","Engineers":["Broo Tarquin"],"Ingredients":[{"Name":"Nickel","Size":1,"Kind":0},{"Name":"Shield Emitters","Size":1,"Kind":0},{"Name":"Tungsten","Size":1,"Kind":0},{"Name":"Osmium","Size":1,"Kind":2}],"Favorite":false,"Ignored":false,"Grade":3},{"Type":"Burst Laser","Name":"Short Range Blaster","Engineers":["The Dweller","Broo Tarquin"],"Ingredients":[{"Name":"Nickel","Size":1,"Kind":0}],"Favorite":false,"Ignored":false,"Grade":1},{"Type":"Burst Laser","Name":"Short Range Blaster","Engineers":["The Dweller","Broo Tarquin"],"Ingredients":[{"Name":"Nickel","Size":1,"Kind":0},{"Name":"Modified Consumer Firmware","Size":1,"Kind":1},{"Name":"Insulating Membrane","Size":1,"Kind":2}],"Favorite":false,"Ignored":false,"Grade":2},{"Type":"Burst Laser","Name":"Short Range Blaster","Engineers":["Broo Tarquin"],"Ingredients":[{"Name":"Nickel","Size":1,"Kind":0},{"Name":"Modified Consumer Firmware","Size":1,"Kind":1},{"Name":"Electrochemical Arrays","Size":1,"Kind":0},{"Name":"Neofabric Insulation","Size":1,"Kind":2}],"Favorite":false,"Ignored":false,"Grade":3},{"Type":"Burst Laser","Name":"Long Range Weapon","Engineers":["The Dweller","Broo Tarquin"],"Ingredients":[{"Name":"Sulphur","Size":1,"Kind":0}],"Favorite":false,"Ignored":false,"Grade":1},{"Type":"Burst Laser","Name":"Long Range Weapon","Engineers":["The Dweller","Broo Tarquin"],"Ingredients":[{"Name":"Sulphur","Size":1,"Kind":0},{"Name":"Modified Consumer Firmware","Size":1,"Kind":1},{"Name":"Insulating Membrane","Size":1,"Kind":2}],"Favorite":false,"Ignored":false,"Grade":2},{"Type":"Burst Laser","Name":"Long Range Weapon","Engineers":["Broo Tarquin"],"Ingredients":[{"Name":"Sulphur","Size":1,"Kind":0},{"Name":"Modified Consumer Firmware","Size":1,"Kind":1},{"Name":"Focus Crystals","Size":1,"Kind":0},{"Name":"Neofabric Insulation","Size":1,"Kind":2}],"Favorite":false,"Ignored":false,"Grade":3},{"Type":"Burst Laser","Name":"Overcharged Weapon","Engineers":["The Dweller","Broo Tarquin"],"Ingredients":[{"Name":"Nickel","Size":1,"Kind":0}],"Favorite":false,"Ignored":false,"Grade":1},{"Type":"Burst Laser","Name":"Overcharged Weapon","Engineers":["The Dweller","Broo Tarquin"],"Ingredients":[{"Name":"Nickel","Size":1,"Kind":0},{"Name":"Conductive Components","Size":1,"Kind":0},{"Name":"Praseodymium","Size":1,"Kind":2}],"Favorite":false,"Ignored":false,"Grade":2},{"Type":"Burst Laser","Name":"Overcharged Weapon","Engineers":["Broo Tarquin"],"Ingredients":[{"Name":"Nickel","Size":1,"Kind":0},{"Name":"Conductive Components","Size":1,"Kind":0},{"Name":"Electrochemical Arrays","Size":1,"Kind":0},{"Name":"Articulation Motors","Size":1,"Kind":2}],"Favorite":false,"Ignored":false,"Grade":3},{"Type":"Beam Laser","Name":"Light Weight Mount","Engineers":["The Dweller","Broo Tarquin"],"Ingredients":[{"Name":"Phosphorus","Size":1,"Kind":0}],"Favorite":false,"Ignored":false,"Grade":1},{"Type":"Beam Laser","Name":"Light Weight Mount","Engineers":["The Dweller"],"Ingredients":[{"Name":"Salvaged Alloys","Size":1,"Kind":0},{"Name":"Manganese","Size":1,"Kind":0},{"Name":"CMM Composite","Size":1,"Kind":2}],"Favorite":false,"Ignored":false,"Grade":2},{"Type":"Beam Laser","Name":"Long Range Weapon","Engineers":["The Dweller","Broo Tarquin"],"Ingredients":[{"Name":"Sulphur","Size":1,"Kind":0}],"Favorite":false,"Ignored":false,"Grade":1},{"Type":"Beam Laser","Name":"Long Range Weapon","Engineers":["The Dweller"],"Ingredients":[{"Name":"Sulphur","Size":1,"Kind":0},{"Name":"Modified Consumer Firmware","Size":1,"Kind":1},{"Name":"Insulating Membrane","Size":1,"Kind":2}],"Favorite":false,"Ignored":false,"Grade":2},{"Type":"Beam Laser","Name":"Short Range Blaster","Engineers":["The Dweller","Broo Tarquin"],"Ingredients":[{"Name":"Nickel","Size":1,"Kind":0}],"Favorite":false,"Ignored":false,"Grade":1},{"Type":"Beam Laser","Name":"Short Range Blaster","Engineers":["The Dweller"],"Ingredients":[{"Name":"Nickel","Size":1,"Kind":0},{"Name":"Modified Consumer Firmware","Size":1,"Kind":1},{"Name":"Insulating Membrane","Size":1,"Kind":2}],"Favorite":false,"Ignored":false,"Grade":2},{"Type":"Beam Laser","Name":"Sturdy Mount","Engineers":["The Dweller","Broo Tarquin"],"Ingredients":[{"Name":"Nickel","Size":1,"Kind":0}],"Favorite":false,"Ignored":false,"Grade":1},{"Type":"Beam Laser","Name":"Sturdy Mount","Engineers":["The Dweller"],"Ingredients":[{"Name":"Nickel","Size":1,"Kind":0},{"Name":"Shield Emitters","Size":1,"Kind":0},{"Name":"HN Shock Mount","Size":1,"Kind":2}],"Favorite":false,"Ignored":false,"Grade":2},{"Type":"Hull Reinforcement","Name":"Lightweight Hull Reinforcement","Engineers":["Selene Jean"],"Ingredients":[{"Name":"Iron","Size":1,"Kind":0}],"Favorite":false,"Ignored":false,"Grade":1},{"Type":"Hull Reinforcement","Name":"Lightweight Hull Reinforcement","Engineers":["Selene Jean"],"Ingredients":[{"Name":"Iron","Size":1,"Kind":0},{"Name":"Conductive Components","Size":1,"Kind":0},{"Name":"HN Shock Mount","Size":1,"Kind":2}],"Favorite":false,"Ignored":false,"Grade":2},{"Type":"Hull Reinforcement","Name":"Lightweight Hull Reinforcement","Engineers":["Selene Jean"],"Ingredients":[{"Name":"Iron","Size":1,"Kind":0},{"Name":"Conductive Components","Size":1,"Kind":0},{"Name":"High Density Composites","Size":1,"Kind":0},{"Name":"Telemetry Suite","Size":1,"Kind":2}],"Favorite":false,"Ignored":false,"Grade":3},{"Type":"Hull Reinforcement","Name":"Lightweight Hull Reinforcement","Engineers":["Selene Jean"],"Ingredients":[{"Name":"Germanium","Size":1,"Kind":0},{"Name":"Conductive Ceramics","Size":1,"Kind":0},{"Name":"Proprietary Composites","Size":1,"Kind":0},{"Name":"Hardware Diagnostic Sensor","Size":1,"Kind":2}],"Favorite":false,"Ignored":false,"Grade":4},{"Type":"Hull Reinforcement","Name":"Lightweight Hull Reinforcement","Engineers":["Selene Jean"],"Ingredients":[{"Name":"Conductive Ceramics","Size":1,"Kind":0},{"Name":"Tin","Size":1,"Kind":0},{"Name":"Military Grade Alloys","Size":1,"Kind":0},{"Name":"Hardware Diagnostic Sensor","Size":1,"Kind":2}],"Favorite":false,"Ignored":false,"Grade":5},{"Type":"Hull Reinforcement","Name":"Blast Resistant Hull Reinforcement","Engineers":["Selene Jean"],"Ingredients":[{"Name":"Nickel","Size":1,"Kind":0}],"Favorite":false,"Ignored":false,"Grade":1},{"Type":"Hull Reinforcement","Name":"Blast Resistant Hull Reinforcement","Engineers":["Selene Jean"],"Ingredients":[{"Name":"Carbon","Size":1,"Kind":0},{"Name":"Zinc","Size":1,"Kind":0},{"Name":"CMM Composite","Size":1,"Kind":2}],"Favorite":false,"Ignored":false,"Grade":2},{"Type":"Hull Reinforcement","Name":"Blast Resistant Hull Reinforcement","Engineers":["Selene Jean"],"Ingredients":[{"Name":"Vanadium","Size":1,"Kind":0},{"Name":"Zirconium","Size":1,"Kind":0},{"Name":"Salvaged Alloys","Size":1,"Kind":0},{"Name":"Osmium","Size":1,"Kind":2}],"Favorite":false,"Ignored":false,"Grade":3},{"Type":"Hull Reinforcement","Name":"Heavy Duty Hull Reinforcement","Engineers":["Selene Jean"],"Ingredients":[{"Name":"Carbon","Size":1,"Kind":0}],"Favorite":false,"Ignored":false,"Grade":1},{"Type":"Hull Reinforcement","Name":"Heavy Duty Hull Reinforcement","Engineers":["Selene Jean"],"Ingredients":[{"Name":"Carbon","Size":1,"Kind":0},{"Name":"Shield Emitters","Size":1,"Kind":0},{"Name":"Articulation Motors","Size":1,"Kind":2}],"Favorite":false,"Ignored":false,"Grade":2},{"Type":"Hull Reinforcement","Name":"Heavy Duty Hull Reinforcement","Engineers":["Selene Jean"],"Ingredients":[{"Name":"Carbon","Size":1,"Kind":0},{"Name":"Shield Emitters","Size":1,"Kind":0},{"Name":"High Density Composites","Size":1,"Kind":0},{"Name":"Reinforced Mounting Plate","Size":1,"Kind":2}],"Favorite":false,"Ignored":false,"Grade":3},{"Type":"Hull Reinforcement","Name":"Heavy Duty Hull Reinforcement","Engineers":["Selene Jean"],"Ingredients":[{"Name":"Vanadium","Size":1,"Kind":0},{"Name":"Shielding Sensors","Size":1,"Kind":0},{"Name":"Proprietary Composites","Size":1,"Kind":0},{"Name":"Reinforced Mounting Plate","Size":1,"Kind":2}],"Favorite":false,"Ignored":false,"Grade":4},{"Type":"Hull Reinforcement","Name":"Heavy Duty Hull Reinforcement","Engineers":["Selene Jean"],"Ingredients":[{"Name":"Tungsten","Size":1,"Kind":0},{"Name":"Compound Shielding","Size":1,"Kind":0},{"Name":"Core Dynamics Composites","Size":1,"Kind":0},{"Name":"Reinforced Mounting Plate","Size":1,"Kind":2}],"Favorite":false,"Ignored":false,"Grade":5},{"Type":"Hull Reinforcement","Name":"Kinetic Resistant Hull Reinforcement","Engineers":["Selene Jean"],"Ingredients":[{"Name":"Nickel","Size":1,"Kind":0}],"Favorite":false,"Ignored":false,"Grade":1},{"Type":"Hull Reinforcement","Name":"Kinetic Resistant Hull Reinforcement","Engineers":["Selene Jean"],"Ingredients":[{"Name":"Nickel","Size":1,"Kind":0},{"Name":"Vanadium","Size":1,"Kind":0},{"Name":"Micro-Weave Cooling Hoses","Size":1,"Kind":2}],"Favorite":false,"Ignored":false,"Grade":2},{"Type":"Hull Reinforcement","Name":"Kinetic Resistant Hull Reinforcement","Engineers":["Selene Jean"],"Ingredients":[{"Name":"Salvaged Alloys","Size":1,"Kind":0},{"Name":"Vanadium","Size":1,"Kind":0},{"Name":"High Density Composites","Size":1,"Kind":0},{"Name":"CMM Composite","Size":1,"Kind":2}],"Favorite":false,"Ignored":false,"Grade":3},{"Type":"Hull Reinforcement","Name":"Thermal Resistant Hull Reinforcement","Engineers":["Selene Jean"],"Ingredients":[{"Name":"Heat Conduction Wiring","Size":1,"Kind":0}],"Favorite":false,"Ignored":false,"Grade":1},{"Type":"Hull Reinforcement","Name":"Thermal Resistant Hull Reinforcement","Engineers":["Selene Jean"],"Ingredients":[{"Name":"Nickel","Size":1,"Kind":0},{"Name":"Heat Dispersion Plate","Size":1,"Kind":0},{"Name":"Neofabric Insulation","Size":1,"Kind":2}],"Favorite":false,"Ignored":false,"Grade":2},{"Type":"Hull Reinforcement","Name":"Thermal Resistant Hull Reinforcement","Engineers":["Selene Jean"],"Ingredients":[{"Name":"Vanadium","Size":1,"Kind":0},{"Name":"Salvaged Alloys","Size":1,"Kind":0},{"Name":"Heat Exchangers","Size":1,"Kind":0},{"Name":"Bromellite","Size":1,"Kind":2}],"Favorite":false,"Ignored":false,"Grade":3},{"Type":"Plasma Accelerators","Name":"Efficient Weapon","Engineers":["Zacariah Nemo"],"Ingredients":[{"Name":"Sulphur","Size":1,"Kind":0}],"Favorite":false,"Ignored":false,"Grade":1},{"Type":"Plasma Accelerators","Name":"Efficient Weapon","Engineers":["Zacariah Nemo"],"Ingredients":[{"Name":"Sulphur","Size":1,"Kind":0},{"Name":"Heat Dispersion Plate","Size":1,"Kind":0},{"Name":"Micro-Weave Cooling Hoses","Size":1,"Kind":2}],"Favorite":false,"Ignored":false,"Grade":2},{"Type":"Plasma Accelerators","Name":"Focused Weapon","Engineers":["Zacariah Nemo"],"Ingredients":[{"Name":"Iron","Size":1,"Kind":0}],"Favorite":false,"Ignored":false,"Grade":1},{"Type":"Plasma Accelerators","Name":"Focused Weapon","Engineers":["Zacariah Nemo"],"Ingredients":[{"Name":"Iron","Size":1,"Kind":0},{"Name":"Conductive Components","Size":1,"Kind":0},{"Name":"Micro Controllers","Size":1,"Kind":2}],"Favorite":false,"Ignored":false,"Grade":2},{"Type":"Plasma Accelerators","Name":"Light Weight Mount","Engineers":["Zacariah Nemo"],"Ingredients":[{"Name":"Phosphorus","Size":1,"Kind":0}],"Favorite":false,"Ignored":false,"Grade":1},{"Type":"Plasma Accelerators","Name":"Light Weight Mount","Engineers":["Zacariah Nemo"],"Ingredients":[{"Name":"Salvaged Alloys","Size":1,"Kind":0},{"Name":"Manganese","Size":1,"Kind":0},{"Name":"CMM Composite","Size":1,"Kind":2}],"Favorite":false,"Ignored":false,"Grade":2},{"Type":"Plasma Accelerators","Name":"Overcharged Weapon","Engineers":["Zacariah Nemo"],"Ingredients":[{"Name":"Nickel","Size":1,"Kind":0}],"Favorite":false,"Ignored":false,"Grade":1},{"Type":"Plasma Accelerators","Name":"Overcharged Weapon","Engineers":["Zacariah Nemo"],"Ingredients":[{"Name":"Nickel","Size":1,"Kind":0},{"Name":"Conductive Components","Size":1,"Kind":0},{"Name":"Praseodymium","Size":1,"Kind":2}],"Favorite":false,"Ignored":false,"Grade":2},{"Type":"Plasma Accelerators","Name":"Rapid Fire Modification","Engineers":["Zacariah Nemo"],"Ingredients":[{"Name":"Mechanical Scrap","Size":1,"Kind":0}],"Favorite":false,"Ignored":false,"Grade":1},{"Type":"Plasma Accelerators","Name":"Rapid Fire Modification","Engineers":["Zacariah Nemo"],"Ingredients":[{"Name":"Mechanical Scrap","Size":1,"Kind":0},{"Name":"Heat Dispersion Plate","Size":1,"Kind":0},{"Name":"HN Shock Mount","Size":1,"Kind":2}],"Favorite":false,"Ignored":false,"Grade":2},{"Type":"Plasma Accelerators","Name":"Sturdy Mount","Engineers":["Zacariah Nemo"],"Ingredients":[{"Name":"Nickel","Size":1,"Kind":0}],"Favorite":false,"Ignored":false,"Grade":1},{"Type":"Plasma Accelerators","Name":"Sturdy Mount","Engineers":["Zacariah Nemo"],"Ingredients":[{"Name":"Nickel","Size":1,"Kind":0},{"Name":"Shield Emitters","Size":1,"Kind":0},{"Name":"HN Shock Mount","Size":1,"Kind":2}],"Favorite":false,"Ignored":false,"Grade":2},{"Type":"Interdictor (FSD)","Name":"Expanded FSD Interdictor Capture Arc","Engineers":["Bris Dekker"],"Ingredients":[{"Name":"Mechanical Scrap","Size":1,"Kind":0}],"Favorite":false,"Ignored":false,"Grade":1},{"Type":"Interdictor (FSD)","Name":"Expanded FSD Interdictor Capture Arc","Engineers":["Bris Dekker"],"Ingredients":[{"Name":"Unusual Encrypted Files","Size":1,"Kind":1},{"Name":"Mechanical Equipment","Size":1,"Kind":0}],"Favorite":false,"Ignored":false,"Grade":2},{"Type":"Interdictor (FSD)","Name":"Expanded FSD Interdictor Capture Arc","Engineers":["Bris Dekker"],"Ingredients":[{"Name":"Grid Resistors","Size":1,"Kind":0},{"Name":"Tagged Encryption Codes","Size":1,"Kind":1},{"Name":"Mechanical Components","Size":1,"Kind":0}],"Favorite":false,"Ignored":false,"Grade":3},{"Type":"Interdictor (FSD)","Name":"Expanded FSD Interdictor Capture Arc","Engineers":["Bris Dekker"],"Ingredients":[{"Name":"Divergent Scan Data","Size":1,"Kind":1},{"Name":"Mechanical Equipment","Size":1,"Kind":0},{"Name":"Strange Wake Solutions","Size":1,"Kind":1}],"Favorite":false,"Ignored":false,"Grade":4},{"Type":"Interdictor (FSD)","Name":"Longer Range FSD Interdictor","Engineers":["Bris Dekker"],"Ingredients":[{"Name":"Unusual Encrypted Files","Size":1,"Kind":1}],"Favorite":false,"Ignored":false,"Grade":1},{"Type":"Interdictor (FSD)","Name":"Longer Range FSD Interdictor","Engineers":["Bris Dekker"],"Ingredients":[{"Name":"Atypical Disrupted Wake Echoes","Size":1,"Kind":1},{"Name":"Tagged Encryption Codes","Size":1,"Kind":1}],"Favorite":false,"Ignored":false,"Grade":2},{"Type":"Interdictor (FSD)","Name":"Longer Range FSD Interdictor","Engineers":["Bris Dekker"],"Ingredients":[{"Name":"Anomalous Bulk Scan Data","Size":1,"Kind":1},{"Name":"Anomalous FSD Telemetry","Size":1,"Kind":1},{"Name":"Open Symmetric Keys","Size":1,"Kind":1},{"Name":"Nanobreakers","Size":1,"Kind":2}],"Favorite":false,"Ignored":false,"Grade":3}]